{
"meta":{"test_sets":[],"test_metrics":[],"learn_metrics":[{"best_value":"Min","name":"Logloss"}],"launch_mode":"Train","parameters":"","iteration_count":1000,"learn_sets":["learn"],"name":"experiment"},
"iterations":[
{"learn":[0.6585799329],"iteration":0,"passed_time":0.1729702319,"remaining_time":172.7972616},
{"learn":[0.6304690469],"iteration":1,"passed_time":0.1941220124,"remaining_time":96.86688421},
{"learn":[0.607350627],"iteration":2,"passed_time":0.2146557158,"remaining_time":71.33724954},
{"learn":[0.5919310191],"iteration":3,"passed_time":0.2371509423,"remaining_time":59.05058463},
{"learn":[0.5795665519],"iteration":4,"passed_time":0.2597276969,"remaining_time":51.68581168},
{"learn":[0.5653587924],"iteration":5,"passed_time":0.2833080478,"remaining_time":46.93469992},
{"learn":[0.5548035543],"iteration":6,"passed_time":0.3065442432,"remaining_time":43.4854905},
{"learn":[0.5456200576],"iteration":7,"passed_time":0.3281411629,"remaining_time":40.6895042},
{"learn":[0.5388648842],"iteration":8,"passed_time":0.3463990727,"remaining_time":38.14238678},
{"learn":[0.5329576512],"iteration":9,"passed_time":0.3647573544,"remaining_time":36.11097809},
{"learn":[0.5273455945],"iteration":10,"passed_time":0.3845612657,"remaining_time":34.5755538},
{"learn":[0.5220226298],"iteration":11,"passed_time":0.4071553038,"remaining_time":33.52245335},
{"learn":[0.517769427],"iteration":12,"passed_time":0.4274640806,"remaining_time":32.45438827},
{"learn":[0.5153237295],"iteration":13,"passed_time":0.4431335972,"remaining_time":31.20926621},
{"learn":[0.5077885671],"iteration":14,"passed_time":0.4654580348,"remaining_time":30.56507762},
{"learn":[0.5022737877],"iteration":15,"passed_time":0.4823768047,"remaining_time":29.66617349},
{"learn":[0.4991222358],"iteration":16,"passed_time":0.5017446219,"remaining_time":29.0126449},
{"learn":[0.4968249865],"iteration":17,"passed_time":0.5179423343,"remaining_time":28.25663179},
{"learn":[0.4950222651],"iteration":18,"passed_time":0.5362964753,"remaining_time":27.6898338},
{"learn":[0.4934271675],"iteration":19,"passed_time":0.556998015,"remaining_time":27.29290274},
{"learn":[0.4917629737],"iteration":20,"passed_time":0.5743334276,"remaining_time":26.77487741},
{"learn":[0.4899673632],"iteration":21,"passed_time":0.5935912097,"remaining_time":26.38782741},
{"learn":[0.4870979141],"iteration":22,"passed_time":0.6168159708,"remaining_time":26.20126971},
{"learn":[0.4853433298],"iteration":23,"passed_time":0.6357441238,"remaining_time":25.85359437},
{"learn":[0.4835775411],"iteration":24,"passed_time":0.655605029,"remaining_time":25.56859613},
{"learn":[0.4824021586],"iteration":25,"passed_time":0.6801673935,"remaining_time":25.48011697},
{"learn":[0.4813858545],"iteration":26,"passed_time":0.699048506,"remaining_time":25.1916369},
{"learn":[0.4804258754],"iteration":27,"passed_time":0.7206809329,"remaining_time":25.01792381},
{"learn":[0.4792844237],"iteration":28,"passed_time":0.7378132792,"remaining_time":24.70402394},
{"learn":[0.4770007018],"iteration":29,"passed_time":0.7553276591,"remaining_time":24.42226098},
{"learn":[0.4750968781],"iteration":30,"passed_time":0.771861522,"remaining_time":24.12689725},
{"learn":[0.4743280638],"iteration":31,"passed_time":0.7912897592,"remaining_time":23.93651522},
{"learn":[0.4728885794],"iteration":32,"passed_time":0.8084689979,"remaining_time":23.69059155},
{"learn":[0.4719895797],"iteration":33,"passed_time":0.8264510717,"remaining_time":23.48093339},
{"learn":[0.4709803011],"iteration":34,"passed_time":0.8409642648,"remaining_time":23.18658616},
{"learn":[0.4700431154],"iteration":35,"passed_time":0.8567488503,"remaining_time":22.94183032},
{"learn":[0.4693256722],"iteration":36,"passed_time":0.8724332854,"remaining_time":22.7068447},
{"learn":[0.4680343813],"iteration":37,"passed_time":0.8877013229,"remaining_time":22.47285981},
{"learn":[0.4671563431],"iteration":38,"passed_time":0.9061858025,"remaining_time":22.32934759},
{"learn":[0.4666127017],"iteration":39,"passed_time":0.9221725178,"remaining_time":22.13214043},
{"learn":[0.4662099991],"iteration":40,"passed_time":0.9400862759,"remaining_time":21.98884728},
{"learn":[0.4657849093],"iteration":41,"passed_time":0.9566917019,"remaining_time":21.82168215},
{"learn":[0.4652457144],"iteration":42,"passed_time":0.9734886902,"remaining_time":21.66578318},
{"learn":[0.4646991907],"iteration":43,"passed_time":0.9900983881,"remaining_time":21.5121377},
{"learn":[0.4641232407],"iteration":44,"passed_time":1.007041615,"remaining_time":21.37166095},
{"learn":[0.4632983329],"iteration":45,"passed_time":1.024104114,"remaining_time":21.23902879},
{"learn":[0.4627917545],"iteration":46,"passed_time":1.042953388,"remaining_time":21.14754422},
{"learn":[0.4625492131],"iteration":47,"passed_time":1.059810526,"remaining_time":21.01957543},
{"learn":[0.4622299141],"iteration":48,"passed_time":1.076057198,"remaining_time":20.88429377},
{"learn":[0.4618624672],"iteration":49,"passed_time":1.094650755,"remaining_time":20.79836434},
{"learn":[0.461483877],"iteration":50,"passed_time":1.114744968,"remaining_time":20.74299949},
{"learn":[0.4608737082],"iteration":51,"passed_time":1.134743798,"remaining_time":20.68725233},
{"learn":[0.4604832768],"iteration":52,"passed_time":1.153333906,"remaining_time":20.6076832},
{"learn":[0.4601396867],"iteration":53,"passed_time":1.174184198,"remaining_time":20.56996762},
{"learn":[0.4596917644],"iteration":54,"passed_time":1.195750093,"remaining_time":20.54516069},
{"learn":[0.4593100887],"iteration":55,"passed_time":1.213092517,"remaining_time":20.44927386},
{"learn":[0.4588258383],"iteration":56,"passed_time":1.233536765,"remaining_time":20.40745911},
{"learn":[0.4583829583],"iteration":57,"passed_time":1.253803116,"remaining_time":20.36349198},
{"learn":[0.4578872595],"iteration":58,"passed_time":1.275454033,"remaining_time":20.34241094},
{"learn":[0.4576114478],"iteration":59,"passed_time":1.294538131,"remaining_time":20.28109738},
{"learn":[0.4573317445],"iteration":60,"passed_time":1.313892634,"remaining_time":20.22533088},
{"learn":[0.4569258049],"iteration":61,"passed_time":1.329254091,"remaining_time":20.11032802},
{"learn":[0.4565250709],"iteration":62,"passed_time":1.345736161,"remaining_time":20.01515528},
{"learn":[0.4562188363],"iteration":63,"passed_time":1.41115018,"remaining_time":20.63807138},
{"learn":[0.455997946],"iteration":64,"passed_time":1.430458608,"remaining_time":20.57659689},
{"learn":[0.4557859701],"iteration":65,"passed_time":1.446977706,"remaining_time":20.47692693},
{"learn":[0.4554834207],"iteration":66,"passed_time":1.463456087,"remaining_time":20.37917207},
{"learn":[0.455082861],"iteration":67,"passed_time":1.484045447,"remaining_time":20.3401523},
{"learn":[0.454910562],"iteration":68,"passed_time":1.505721812,"remaining_time":20.31633344},
{"learn":[0.4545833256],"iteration":69,"passed_time":1.523508699,"remaining_time":20.24090129},
{"learn":[0.4544558845],"iteration":70,"passed_time":1.540037357,"remaining_time":20.15062965},
{"learn":[0.4541979453],"iteration":71,"passed_time":1.560887892,"remaining_time":20.1181106},
{"learn":[0.4539807204],"iteration":72,"passed_time":1.577981089,"remaining_time":20.03819821},
{"learn":[0.4537415881],"iteration":73,"passed_time":1.596229402,"remaining_time":19.97443819},
{"learn":[0.4535543879],"iteration":74,"passed_time":1.614629516,"remaining_time":19.91376403},
{"learn":[0.4532866628],"iteration":75,"passed_time":1.63084144,"remaining_time":19.82759856},
{"learn":[0.4532858042],"iteration":76,"passed_time":1.645374724,"remaining_time":19.72312818},
{"learn":[0.4530915375],"iteration":77,"passed_time":1.673025571,"remaining_time":19.77602021},
{"learn":[0.4527931336],"iteration":78,"passed_time":1.691104814,"remaining_time":19.71528524},
{"learn":[0.4527761999],"iteration":79,"passed_time":1.707543351,"remaining_time":19.63674854},
{"learn":[0.4526084723],"iteration":80,"passed_time":1.724606013,"remaining_time":19.56682625},
{"learn":[0.4523313585],"iteration":81,"passed_time":1.742220462,"remaining_time":19.50437054},
{"learn":[0.4520034212],"iteration":82,"passed_time":1.757518938,"remaining_time":19.41740802},
{"learn":[0.4518884],"iteration":83,"passed_time":1.77569365,"remaining_time":19.36351647},
{"learn":[0.4517517201],"iteration":84,"passed_time":1.792238137,"remaining_time":19.29291641},
{"learn":[0.4516696247],"iteration":85,"passed_time":1.810003858,"remaining_time":19.23655263},
{"learn":[0.4514809374],"iteration":86,"passed_time":1.826596965,"remaining_time":19.16877045},
{"learn":[0.4512829282],"iteration":87,"passed_time":1.845155881,"remaining_time":19.12252458},
{"learn":[0.4511492832],"iteration":88,"passed_time":1.862796723,"remaining_time":19.06750353},
{"learn":[0.4510201973],"iteration":89,"passed_time":1.879521414,"remaining_time":19.00404985},
{"learn":[0.4508621152],"iteration":90,"passed_time":1.893617966,"remaining_time":18.91537067},
{"learn":[0.450718488],"iteration":91,"passed_time":1.909127843,"remaining_time":18.84226175},
{"learn":[0.4504659989],"iteration":92,"passed_time":1.925122954,"remaining_time":18.77512386},
{"learn":[0.4503807719],"iteration":93,"passed_time":1.941038154,"remaining_time":18.70830391},
{"learn":[0.4500989089],"iteration":94,"passed_time":1.964474684,"remaining_time":18.7142062},
{"learn":[0.4499462716],"iteration":95,"passed_time":1.979375985,"remaining_time":18.63912386},
{"learn":[0.449753219],"iteration":96,"passed_time":1.994461673,"remaining_time":18.56699887},
{"learn":[0.4496602038],"iteration":97,"passed_time":2.007945638,"remaining_time":18.48129556},
{"learn":[0.4494958984],"iteration":98,"passed_time":2.027019357,"remaining_time":18.44792364},
{"learn":[0.449379675],"iteration":99,"passed_time":2.046479809,"remaining_time":18.41831828},
{"learn":[0.4491777542],"iteration":100,"passed_time":2.062268372,"remaining_time":18.35623036},
{"learn":[0.4490813863],"iteration":101,"passed_time":2.077235233,"remaining_time":18.28781607},
{"learn":[0.4486678763],"iteration":102,"passed_time":2.090742625,"remaining_time":18.20772946},
{"learn":[0.4484593384],"iteration":103,"passed_time":2.105355844,"remaining_time":18.13845035},
{"learn":[0.4483606859],"iteration":104,"passed_time":2.120507817,"remaining_time":18.07480472},
{"learn":[0.4482198164],"iteration":105,"passed_time":2.137128515,"remaining_time":18.02446125},
{"learn":[0.4480681737],"iteration":106,"passed_time":2.155519287,"remaining_time":17.98952077},
{"learn":[0.4478039638],"iteration":107,"passed_time":2.170672674,"remaining_time":17.92814838},
{"learn":[0.4476655364],"iteration":108,"passed_time":2.185795586,"remaining_time":17.86737493},
{"learn":[0.4475917689],"iteration":109,"passed_time":2.19937697,"remaining_time":17.79495912},
{"learn":[0.4475164167],"iteration":110,"passed_time":2.213292456,"remaining_time":17.72627922},
{"learn":[0.4474416113],"iteration":111,"passed_time":2.227012793,"remaining_time":17.65703},
{"learn":[0.4473468415],"iteration":112,"passed_time":2.237913639,"remaining_time":17.56663183},
{"learn":[0.4471987025],"iteration":113,"passed_time":2.249835719,"remaining_time":17.48556532},
{"learn":[0.4471394562],"iteration":114,"passed_time":2.262885535,"remaining_time":17.41437999},
{"learn":[0.4469869035],"iteration":115,"passed_time":2.277260404,"remaining_time":17.3542948},
{"learn":[0.446851442],"iteration":116,"passed_time":2.288618271,"remaining_time":17.27222165},
{"learn":[0.4467103339],"iteration":117,"passed_time":2.301810104,"remaining_time":17.20505518},
{"learn":[0.4466249268],"iteration":118,"passed_time":2.313926044,"remaining_time":17.13083063},
{"learn":[0.4465573684],"iteration":119,"passed_time":2.328111422,"remaining_time":17.07281709},
{"learn":[0.4464754058],"iteration":120,"passed_time":2.341920202,"remaining_time":17.01279221},
{"learn":[0.4463072546],"iteration":121,"passed_time":2.354387897,"remaining_time":16.94387355},
{"learn":[0.4463069676],"iteration":122,"passed_time":2.361457204,"remaining_time":16.83738186},
{"learn":[0.4461814506],"iteration":123,"passed_time":2.375623985,"remaining_time":16.78263396},
{"learn":[0.4460923599],"iteration":124,"passed_time":2.389626089,"remaining_time":16.72738262},
{"learn":[0.4459392295],"iteration":125,"passed_time":2.400813008,"remaining_time":16.65325849},
{"learn":[0.445812514],"iteration":126,"passed_time":2.413525132,"remaining_time":16.59060977},
{"learn":[0.4457210733],"iteration":127,"passed_time":2.429133681,"remaining_time":16.5484732},
{"learn":[0.4455990632],"iteration":128,"passed_time":2.446923491,"remaining_time":16.52147567},
{"learn":[0.4454924959],"iteration":129,"passed_time":2.462157267,"remaining_time":16.47751401},
{"learn":[0.4453920575],"iteration":130,"passed_time":2.47747521,"remaining_time":16.43454929},
{"learn":[0.4453140848],"iteration":131,"passed_time":2.492747263,"remaining_time":16.3917017},
{"learn":[0.4451777689],"iteration":132,"passed_time":2.508262043,"remaining_time":16.35085106},
{"learn":[0.4451159856],"iteration":133,"passed_time":2.522101466,"remaining_time":16.29955126},
{"learn":[0.4450462771],"iteration":134,"passed_time":2.534676617,"remaining_time":16.24070573},
{"learn":[0.4450446126],"iteration":135,"passed_time":2.541031171,"remaining_time":16.14302156},
{"learn":[0.4450145031],"iteration":136,"passed_time":2.553832401,"remaining_time":16.08728002},
{"learn":[0.4449640336],"iteration":137,"passed_time":2.567213842,"remaining_time":16.03578501},
{"learn":[0.4448964566],"iteration":138,"passed_time":2.581891619,"remaining_time":15.99286823},
{"learn":[0.4445613532],"iteration":139,"passed_time":2.595393223,"remaining_time":15.9431298},
{"learn":[0.4444682946],"iteration":140,"passed_time":2.610574022,"remaining_time":15.90413535},
{"learn":[0.4443809044],"iteration":141,"passed_time":2.625171483,"remaining_time":15.86195163},
{"learn":[0.4442962322],"iteration":142,"passed_time":2.640323541,"remaining_time":15.82347745},
{"learn":[0.4442511028],"iteration":143,"passed_time":2.654949705,"remaining_time":15.78220103},
{"learn":[0.4442039135],"iteration":144,"passed_time":2.668262812,"remaining_time":15.73354968},
{"learn":[0.4441607574],"iteration":145,"passed_time":2.688151331,"remaining_time":15.72384409},
{"learn":[0.4440853005],"iteration":146,"passed_time":2.703390656,"remaining_time":15.68702197},
{"learn":[0.4440836544],"iteration":147,"passed_time":2.709652704,"remaining_time":15.59881151},
{"learn":[0.4439943611],"iteration":148,"passed_time":2.724285917,"remaining_time":15.55951218},
{"learn":[0.4439557928],"iteration":149,"passed_time":2.741689886,"remaining_time":15.53624269},
{"learn":[0.4438809249],"iteration":150,"passed_time":2.75538229,"remaining_time":15.49218254},
{"learn":[0.4438587895],"iteration":151,"passed_time":2.769684634,"remaining_time":15.4519248},
{"learn":[0.4437736223],"iteration":152,"passed_time":2.784989606,"remaining_time":15.41755684},
{"learn":[0.4436612274],"iteration":153,"passed_time":2.802471021,"remaining_time":15.39539275},
{"learn":[0.4435887533],"iteration":154,"passed_time":2.816202005,"remaining_time":15.35284319},
{"learn":[0.443332064],"iteration":155,"passed_time":2.833161405,"remaining_time":15.32812965},
{"learn":[0.443260119],"iteration":156,"passed_time":2.852448755,"remaining_time":15.31601465},
{"learn":[0.4431668257],"iteration":157,"passed_time":2.867752434,"remaining_time":15.28257943},
{"learn":[0.4430374985],"iteration":158,"passed_time":2.882314587,"remaining_time":15.24545011},
{"learn":[0.4429636999],"iteration":159,"passed_time":2.896656444,"remaining_time":15.20744633},
{"learn":[0.4426944774],"iteration":160,"passed_time":2.91153877,"remaining_time":15.17255297},
{"learn":[0.4425688419],"iteration":161,"passed_time":2.928481335,"remaining_time":15.14856394},
{"learn":[0.4424584631],"iteration":162,"passed_time":2.948535455,"remaining_time":15.14063912},
{"learn":[0.4423746629],"iteration":163,"passed_time":2.966251513,"remaining_time":15.12064796},
{"learn":[0.4422922567],"iteration":164,"passed_time":2.981684577,"remaining_time":15.08913104},
{"learn":[0.4422207985],"iteration":165,"passed_time":2.9970608,"remaining_time":15.05752233},
{"learn":[0.4422199374],"iteration":166,"passed_time":3.004573097,"remaining_time":14.98688257},
{"learn":[0.4421427852],"iteration":167,"passed_time":3.018173481,"remaining_time":14.94714486},
{"learn":[0.4421366407],"iteration":168,"passed_time":3.029513498,"remaining_time":14.89660187},
{"learn":[0.4420069875],"iteration":169,"passed_time":3.044440449,"remaining_time":14.86403278},
{"learn":[0.4419641842],"iteration":170,"passed_time":3.056939926,"remaining_time":14.81990174},
{"learn":[0.4419304389],"iteration":171,"passed_time":3.070050424,"remaining_time":14.77907995},
{"learn":[0.44168978],"iteration":172,"passed_time":3.083817326,"remaining_time":14.74171635},
{"learn":[0.4416295623],"iteration":173,"passed_time":3.099805151,"remaining_time":14.71516698},
{"learn":[0.4415522619],"iteration":174,"passed_time":3.116319796,"remaining_time":14.69122189},
{"learn":[0.4414487809],"iteration":175,"passed_time":3.132279976,"remaining_time":14.66476534},
{"learn":[0.441444306],"iteration":176,"passed_time":3.146023489,"remaining_time":14.62812051},
{"learn":[0.4413918644],"iteration":177,"passed_time":3.161716836,"remaining_time":14.6007373},
{"learn":[0.4413538063],"iteration":178,"passed_time":3.176842036,"remaining_time":14.57087883},
{"learn":[0.4412850723],"iteration":179,"passed_time":3.190508865,"remaining_time":14.53454039},
{"learn":[0.4412217781],"iteration":180,"passed_time":3.203083599,"remaining_time":14.49351087},
{"learn":[0.4411380478],"iteration":181,"passed_time":3.215974112,"remaining_time":14.45421332},
{"learn":[0.4411124036],"iteration":182,"passed_time":3.22964728,"remaining_time":14.41869851},
{"learn":[0.4410500734],"iteration":183,"passed_time":3.244357931,"remaining_time":14.38802213},
{"learn":[0.4410293388],"iteration":184,"passed_time":3.258859037,"remaining_time":14.35659521},
{"learn":[0.4410246324],"iteration":185,"passed_time":3.269627387,"remaining_time":14.30901448},
{"learn":[0.4409648151],"iteration":186,"passed_time":3.284006967,"remaining_time":14.27752762},
{"learn":[0.4409121666],"iteration":187,"passed_time":3.300860147,"remaining_time":14.25690659},
{"learn":[0.440867986],"iteration":188,"passed_time":3.314974112,"remaining_time":14.22457145},
{"learn":[0.4408255233],"iteration":189,"passed_time":3.330685591,"remaining_time":14.19923857},
{"learn":[0.4407726215],"iteration":190,"passed_time":3.344543994,"remaining_time":14.16615755},
{"learn":[0.4406754277],"iteration":191,"passed_time":3.359824775,"remaining_time":14.13926259},
{"learn":[0.4406331777],"iteration":192,"passed_time":3.375784696,"remaining_time":14.11532772},
{"learn":[0.4406043717],"iteration":193,"passed_time":3.39081936,"remaining_time":14.08763095},
{"learn":[0.4405592156],"iteration":194,"passed_time":3.405409149,"remaining_time":14.05822751},
{"learn":[0.4405594534],"iteration":195,"passed_time":3.412160802,"remaining_time":13.99682288},
{"learn":[0.440484073],"iteration":196,"passed_time":3.42938034,"remaining_time":13.97864169},
{"learn":[0.4404325482],"iteration":197,"passed_time":3.443600762,"remaining_time":13.94832228},
{"learn":[0.4404087411],"iteration":198,"passed_time":3.458285567,"remaining_time":13.92003387},
{"learn":[0.4403693126],"iteration":199,"passed_time":3.473234673,"remaining_time":13.89293869},
{"learn":[0.440307897],"iteration":200,"passed_time":3.48734277,"remaining_time":13.86262126},
{"learn":[0.4402138647],"iteration":201,"passed_time":3.501274823,"remaining_time":13.83176885},
{"learn":[0.4401778961],"iteration":202,"passed_time":3.516294731,"remaining_time":13.80535419},
{"learn":[0.4401057287],"iteration":203,"passed_time":3.532052811,"remaining_time":13.78193156},
{"learn":[0.4400915461],"iteration":204,"passed_time":3.54680922,"remaining_time":13.75469917},
{"learn":[0.4400583749],"iteration":205,"passed_time":3.561486286,"remaining_time":13.72728209},
{"learn":[0.439955232],"iteration":206,"passed_time":3.576691719,"remaining_time":13.70201224},
{"learn":[0.4398943824],"iteration":207,"passed_time":3.594309153,"remaining_time":13.68602331},
{"learn":[0.4398458287],"iteration":208,"passed_time":3.610715339,"remaining_time":13.66543461},
{"learn":[0.4398153691],"iteration":209,"passed_time":3.626393747,"remaining_time":13.6421479},
{"learn":[0.4397988075],"iteration":210,"passed_time":3.63979483,"remaining_time":13.61041763},
{"learn":[0.4397757964],"iteration":211,"passed_time":3.654612967,"remaining_time":13.58412744},
{"learn":[0.4397528933],"iteration":212,"passed_time":3.671854976,"remaining_time":13.56690078},
{"learn":[0.4397361609],"iteration":213,"passed_time":3.689206663,"remaining_time":13.55007681},
{"learn":[0.4396811102],"iteration":214,"passed_time":3.7066678,"remaining_time":13.53364755},
{"learn":[0.4396472997],"iteration":215,"passed_time":3.726672117,"remaining_time":13.52643953},
{"learn":[0.4396284859],"iteration":216,"passed_time":3.743891423,"remaining_time":13.50906444},
{"learn":[0.4395975139],"iteration":217,"passed_time":3.758943643,"remaining_time":13.48391711},
{"learn":[0.4395827285],"iteration":218,"passed_time":3.771520505,"remaining_time":13.45003431},
{"learn":[0.4395598358],"iteration":219,"passed_time":3.785969628,"remaining_time":13.42298323},
{"learn":[0.4395106658],"iteration":220,"passed_time":3.799360541,"remaining_time":13.39231611},
{"learn":[0.4394818827],"iteration":221,"passed_time":3.813403822,"remaining_time":13.36409087},
{"learn":[0.4394574543],"iteration":222,"passed_time":3.825147464,"remaining_time":13.32798018},
{"learn":[0.4393807458],"iteration":223,"passed_time":3.837433758,"remaining_time":13.29396695},
{"learn":[0.4393394189],"iteration":224,"passed_time":3.850988117,"remaining_time":13.26451463},
{"learn":[0.4392616345],"iteration":225,"passed_time":3.864647831,"remaining_time":13.23556381},
{"learn":[0.439226777],"iteration":226,"passed_time":3.877624376,"remaining_time":13.20442133},
{"learn":[0.439196824],"iteration":227,"passed_time":3.888534169,"remaining_time":13.16644025},
{"learn":[0.4391097628],"iteration":228,"passed_time":3.902347673,"remaining_time":13.13847186},
{"learn":[0.4390050347],"iteration":229,"passed_time":3.915412874,"remaining_time":13.10812136},
{"learn":[0.4389332603],"iteration":230,"passed_time":3.931265467,"remaining_time":13.08719976},
{"learn":[0.4388644411],"iteration":231,"passed_time":3.945224517,"remaining_time":13.06005357},
{"learn":[0.4388327774],"iteration":232,"passed_time":3.958367371,"remaining_time":13.03033379},
{"learn":[0.4388114911],"iteration":233,"passed_time":3.97052158,"remaining_time":12.99751936},
{"learn":[0.4387750194],"iteration":234,"passed_time":3.983897601,"remaining_time":12.96885815},
{"learn":[0.4387432493],"iteration":235,"passed_time":3.996602275,"remaining_time":12.93815313},
{"learn":[0.438685257],"iteration":236,"passed_time":4.009954307,"remaining_time":12.90968412},
{"learn":[0.4386523542],"iteration":237,"passed_time":4.023267713,"remaining_time":12.88121847},
{"learn":[0.4385915215],"iteration":238,"passed_time":4.035176092,"remaining_time":12.84840588},
{"learn":[0.4384429922],"iteration":239,"passed_time":4.04870003,"remaining_time":12.82088343},
{"learn":[0.4383638398],"iteration":240,"passed_time":4.061839742,"remaining_time":12.79226707},
{"learn":[0.4382800822],"iteration":241,"passed_time":4.075522226,"remaining_time":12.76547871},
{"learn":[0.4382466256],"iteration":242,"passed_time":4.088181401,"remaining_time":12.73561037},
{"learn":[0.4382187548],"iteration":243,"passed_time":4.100138772,"remaining_time":12.70370865},
{"learn":[0.438200724],"iteration":244,"passed_time":4.113523362,"remaining_time":12.67636791},
{"learn":[0.4381756399],"iteration":245,"passed_time":4.126920736,"remaining_time":12.64917982},
{"learn":[0.4381440896],"iteration":246,"passed_time":4.140524547,"remaining_time":12.62273273},
{"learn":[0.4381184253],"iteration":247,"passed_time":4.154690345,"remaining_time":12.59809331},
{"learn":[0.4380907664],"iteration":248,"passed_time":4.171875359,"remaining_time":12.58264416},
{"learn":[0.4380649388],"iteration":249,"passed_time":4.183271873,"remaining_time":12.54981562},
{"learn":[0.4380205978],"iteration":250,"passed_time":4.196535046,"remaining_time":12.52272809},
{"learn":[0.4379841662],"iteration":251,"passed_time":4.20950547,"remaining_time":12.49488132},
{"learn":[0.4379205288],"iteration":252,"passed_time":4.223420532,"remaining_time":12.46994126},
{"learn":[0.4379047714],"iteration":253,"passed_time":4.240033781,"remaining_time":12.4530126},
{"learn":[0.437885194],"iteration":254,"passed_time":4.256097961,"remaining_time":12.43448228},
{"learn":[0.4378590969],"iteration":255,"passed_time":4.272055295,"remaining_time":12.4156607},
{"learn":[0.4378319891],"iteration":256,"passed_time":4.285905214,"remaining_time":12.39076877},
{"learn":[0.4377616989],"iteration":257,"passed_time":4.303168439,"remaining_time":12.375779},
{"learn":[0.4377310817],"iteration":258,"passed_time":4.317477152,"remaining_time":12.3523188},
{"learn":[0.4376595425],"iteration":259,"passed_time":4.329764671,"remaining_time":12.32317637},
{"learn":[0.4376427078],"iteration":260,"passed_time":4.343216272,"remaining_time":12.2974591},
{"learn":[0.4375935758],"iteration":261,"passed_time":4.357369171,"remaining_time":12.27381087},
{"learn":[0.4375761786],"iteration":262,"passed_time":4.372702546,"remaining_time":12.25354288},
{"learn":[0.4375394698],"iteration":263,"passed_time":4.386935625,"remaining_time":12.23024477},
{"learn":[0.4375039554],"iteration":264,"passed_time":4.400194599,"remaining_time":12.20431332},
{"learn":[0.4374927744],"iteration":265,"passed_time":4.412607954,"remaining_time":12.17614375},
{"learn":[0.4374797019],"iteration":266,"passed_time":4.427276225,"remaining_time":12.15428267},
{"learn":[0.4374642],"iteration":267,"passed_time":4.442519617,"remaining_time":12.13404612},
{"learn":[0.4374471588],"iteration":268,"passed_time":4.457608307,"remaining_time":12.11342629},
{"learn":[0.4374237324],"iteration":269,"passed_time":4.472298779,"remaining_time":12.09177077},
{"learn":[0.437385459],"iteration":270,"passed_time":4.486355513,"remaining_time":12.06846188},
{"learn":[0.4373647728],"iteration":271,"passed_time":4.501144299,"remaining_time":12.04718033},
{"learn":[0.4373486853],"iteration":272,"passed_time":4.516584596,"remaining_time":12.02768132},
{"learn":[0.4373169932],"iteration":273,"passed_time":4.531953582,"remaining_time":12.008023},
{"learn":[0.4372651505],"iteration":274,"passed_time":4.55061741,"remaining_time":11.99708226},
{"learn":[0.4372363959],"iteration":275,"passed_time":4.566692437,"remaining_time":11.97929465},
{"learn":[0.4372137649],"iteration":276,"passed_time":4.582214541,"remaining_time":11.96007622},
{"learn":[0.4371949406],"iteration":277,"passed_time":4.598280089,"remaining_time":11.94229577},
{"learn":[0.4371790852],"iteration":278,"passed_time":4.6142558,"remaining_time":11.92429546},
{"learn":[0.4371441367],"iteration":279,"passed_time":4.630556556,"remaining_time":11.90714543},
{"learn":[0.4370173896],"iteration":280,"passed_time":4.647659235,"remaining_time":11.89205335},
{"learn":[0.4369542011],"iteration":281,"passed_time":4.663640346,"remaining_time":11.87409138},
{"learn":[0.4369310662],"iteration":282,"passed_time":4.681316265,"remaining_time":11.86043732},
{"learn":[0.4368992925],"iteration":283,"passed_time":4.69797489,"remaining_time":11.84419022},
{"learn":[0.4368759239],"iteration":284,"passed_time":4.712694389,"remaining_time":11.8230754},
{"learn":[0.4368559111],"iteration":285,"passed_time":4.723711733,"remaining_time":11.79276286},
{"learn":[0.4368265296],"iteration":286,"passed_time":4.735659491,"remaining_time":11.76489623},
{"learn":[0.4367996003],"iteration":287,"passed_time":4.750844056,"remaining_time":11.74514225},
{"learn":[0.4367867442],"iteration":288,"passed_time":4.766066966,"remaining_time":11.72551423},
{"learn":[0.4367260661],"iteration":289,"passed_time":4.78225763,"remaining_time":11.70828592},
{"learn":[0.4366822076],"iteration":290,"passed_time":4.798316045,"remaining_time":11.69074253},
{"learn":[0.4366541926],"iteration":291,"passed_time":4.814130403,"remaining_time":11.67261755},
{"learn":[0.436632925],"iteration":292,"passed_time":4.829473122,"remaining_time":11.6533703},
{"learn":[0.4366001463],"iteration":293,"passed_time":4.843381661,"remaining_time":11.63070562},
{"learn":[0.4365733571],"iteration":294,"passed_time":4.854915114,"remaining_time":11.60242426},
{"learn":[0.4365615814],"iteration":295,"passed_time":4.867956463,"remaining_time":11.5778424},
{"learn":[0.436543291],"iteration":296,"passed_time":4.880575032,"remaining_time":11.55233753},
{"learn":[0.4365224521],"iteration":297,"passed_time":4.902127465,"remaining_time":11.5479647},
{"learn":[0.4364405982],"iteration":298,"passed_time":4.91467092,"remaining_time":11.52235557},
{"learn":[0.4364148838],"iteration":299,"passed_time":4.92873831,"remaining_time":11.50038939},
{"learn":[0.4363924526],"iteration":300,"passed_time":4.942395845,"remaining_time":11.47752391},
{"learn":[0.4363645739],"iteration":301,"passed_time":4.958223427,"remaining_time":11.45973494},
{"learn":[0.4363271577],"iteration":302,"passed_time":4.979335198,"remaining_time":11.4541143},
{"learn":[0.4363065488],"iteration":303,"passed_time":4.999089677,"remaining_time":11.44528426},
{"learn":[0.4362967309],"iteration":304,"passed_time":5.017265202,"remaining_time":11.43278464},
{"learn":[0.4362629552],"iteration":305,"passed_time":5.043828398,"remaining_time":11.43927094},
{"learn":[0.4362135264],"iteration":306,"passed_time":5.072452905,"remaining_time":11.45019499},
{"learn":[0.436199078],"iteration":307,"passed_time":5.094854179,"remaining_time":11.44688017},
{"learn":[0.4361771459],"iteration":308,"passed_time":5.116598036,"remaining_time":11.44197166},
{"learn":[0.436151004],"iteration":309,"passed_time":5.138814623,"remaining_time":11.43800674},
{"learn":[0.4361392371],"iteration":310,"passed_time":5.151902636,"remaining_time":11.4137007},
{"learn":[0.4361072937],"iteration":311,"passed_time":5.16667228,"remaining_time":11.39317477},
{"learn":[0.4360525722],"iteration":312,"passed_time":5.178304812,"remaining_time":11.36580002},
{"learn":[0.436004285],"iteration":313,"passed_time":5.190402365,"remaining_time":11.33954147},
{"learn":[0.4359830459],"iteration":314,"passed_time":5.206562209,"remaining_time":11.32220671},
{"learn":[0.4359635366],"iteration":315,"passed_time":5.230696717,"remaining_time":11.322141},
{"learn":[0.4359518382],"iteration":316,"passed_time":5.252497638,"remaining_time":11.31689554},
{"learn":[0.43593227],"iteration":317,"passed_time":5.271857931,"remaining_time":11.30631166},
{"learn":[0.4359021844],"iteration":318,"passed_time":5.294187156,"remaining_time":11.30201083},
{"learn":[0.4358755286],"iteration":319,"passed_time":5.314931021,"remaining_time":11.29422842},
{"learn":[0.4358611951],"iteration":320,"passed_time":5.335449524,"remaining_time":11.28588856},
{"learn":[0.4358311048],"iteration":321,"passed_time":5.357730487,"remaining_time":11.28118407},
{"learn":[0.4358170461],"iteration":322,"passed_time":5.381979354,"remaining_time":11.28049543},
{"learn":[0.435789533],"iteration":323,"passed_time":5.403886455,"remaining_time":11.27477544},
{"learn":[0.4357697773],"iteration":324,"passed_time":5.426141664,"remaining_time":11.26967884},
{"learn":[0.4357477486],"iteration":325,"passed_time":5.44195252,"remaining_time":11.25115337},
{"learn":[0.4357300911],"iteration":326,"passed_time":5.459126716,"remaining_time":11.2354504},
{"learn":[0.4356897388],"iteration":327,"passed_time":5.477363328,"remaining_time":11.22191511},
{"learn":[0.4356829396],"iteration":328,"passed_time":5.500249562,"remaining_time":11.21783421},
{"learn":[0.4356374768],"iteration":329,"passed_time":5.523387366,"remaining_time":11.21415011},
{"learn":[0.4355852905],"iteration":330,"passed_time":5.547465279,"remaining_time":11.21224856},
{"learn":[0.4354977964],"iteration":331,"passed_time":5.566561504,"remaining_time":11.20019001},
{"learn":[0.4354810919],"iteration":332,"passed_time":5.592165375,"remaining_time":11.20112404},
{"learn":[0.4354647406],"iteration":333,"passed_time":5.6139688,"remaining_time":11.19432102},
{"learn":[0.4354520381],"iteration":334,"passed_time":5.636554276,"remaining_time":11.18898088},
{"learn":[0.4354407709],"iteration":335,"passed_time":5.661349126,"remaining_time":11.18790423},
{"learn":[0.4354009939],"iteration":336,"passed_time":5.680594956,"remaining_time":11.1757699},
{"learn":[0.4353762129],"iteration":337,"passed_time":5.704243115,"remaining_time":11.1722158},
{"learn":[0.4353409153],"iteration":338,"passed_time":5.727881982,"remaining_time":11.16852505},
{"learn":[0.4353286148],"iteration":339,"passed_time":5.747055818,"remaining_time":11.15604953},
{"learn":[0.4353198167],"iteration":340,"passed_time":5.779134782,"remaining_time":11.16847455},
{"learn":[0.4353063638],"iteration":341,"passed_time":5.807599734,"remaining_time":11.17368604},
{"learn":[0.4352746445],"iteration":342,"passed_time":5.826738953,"remaining_time":11.16083817},
{"learn":[0.4352312668],"iteration":343,"passed_time":5.843597247,"remaining_time":11.14360405},
{"learn":[0.4352214194],"iteration":344,"passed_time":5.870108069,"remaining_time":11.14469793},
{"learn":[0.435195085],"iteration":345,"passed_time":5.898318211,"remaining_time":11.14884425},
{"learn":[0.4351832907],"iteration":346,"passed_time":5.926666261,"remaining_time":11.1530636},
{"learn":[0.4351634583],"iteration":347,"passed_time":5.955678697,"remaining_time":11.15834055},
{"learn":[0.4351591568],"iteration":348,"passed_time":5.974417,"remaining_time":11.14425635},
{"learn":[0.4351332335],"iteration":349,"passed_time":5.998982563,"remaining_time":11.14096762},
{"learn":[0.4351261922],"iteration":350,"passed_time":6.02233632,"remaining_time":11.13531701},
{"learn":[0.4351112129],"iteration":351,"passed_time":6.046004544,"remaining_time":11.13014473},
{"learn":[0.4351060619],"iteration":352,"passed_time":6.067453522,"remaining_time":11.12080008},
{"learn":[0.4350315657],"iteration":353,"passed_time":6.087520012,"remaining_time":11.1088642},
{"learn":[0.4350184816],"iteration":354,"passed_time":6.111964465,"remaining_time":11.10483684},
{"learn":[0.4349870198],"iteration":355,"passed_time":6.131605309,"remaining_time":11.09200511},
{"learn":[0.4349774002],"iteration":356,"passed_time":6.152018638,"remaining_time":11.08052657},
{"learn":[0.4349621626],"iteration":357,"passed_time":6.174325725,"remaining_time":11.07239418},
{"learn":[0.4349014913],"iteration":358,"passed_time":6.202454974,"remaining_time":11.07457838},
{"learn":[0.4348759369],"iteration":359,"passed_time":6.232407455,"remaining_time":11.07983548},
{"learn":[0.4348583838],"iteration":360,"passed_time":6.258577015,"remaining_time":11.07820142},
{"learn":[0.4348300327],"iteration":361,"passed_time":6.280844512,"remaining_time":11.06955469},
{"learn":[0.4348158251],"iteration":362,"passed_time":6.300521685,"remaining_time":11.05628737},
{"learn":[0.4347946539],"iteration":363,"passed_time":6.323812699,"remaining_time":11.04929911},
{"learn":[0.4347742487],"iteration":364,"passed_time":6.342748421,"remaining_time":11.03464451},
{"learn":[0.4347560244],"iteration":365,"passed_time":6.360134777,"remaining_time":11.01728265},
{"learn":[0.4347444493],"iteration":366,"passed_time":6.377220884,"remaining_time":10.99940278},
{"learn":[0.4347223002],"iteration":367,"passed_time":6.398036838,"remaining_time":10.98793283},
{"learn":[0.4347051996],"iteration":368,"passed_time":6.420647561,"remaining_time":10.97948133},
{"learn":[0.4346924799],"iteration":369,"passed_time":6.441359841,"remaining_time":10.96772081},
{"learn":[0.4346616903],"iteration":370,"passed_time":6.463708443,"remaining_time":10.95868628},
{"learn":[0.434600291],"iteration":371,"passed_time":6.486266417,"remaining_time":10.94993363},
{"learn":[0.4345937665],"iteration":372,"passed_time":6.506694333,"remaining_time":10.9375264},
{"learn":[0.4345452857],"iteration":373,"passed_time":6.531884322,"remaining_time":10.93304702},
{"learn":[0.4345230172],"iteration":374,"passed_time":6.554097847,"remaining_time":10.92349641},
{"learn":[0.4345110679],"iteration":375,"passed_time":6.571780923,"remaining_time":10.90635983},
{"learn":[0.4344872663],"iteration":376,"passed_time":6.59401181,"remaining_time":10.8967357},
{"learn":[0.4344728667],"iteration":377,"passed_time":6.62029766,"remaining_time":10.89371731},
{"learn":[0.4344447146],"iteration":378,"passed_time":6.637065012,"remaining_time":10.87497987},
{"learn":[0.4344171534],"iteration":379,"passed_time":6.649791335,"remaining_time":10.84965955},
{"learn":[0.4344060756],"iteration":380,"passed_time":6.664304122,"remaining_time":10.82730775},
{"learn":[0.4343980486],"iteration":381,"passed_time":6.680538681,"remaining_time":10.80778247},
{"learn":[0.4343851941],"iteration":382,"passed_time":6.704106072,"remaining_time":10.80008733},
{"learn":[0.4343794166],"iteration":383,"passed_time":6.720515502,"remaining_time":10.78082695},
{"learn":[0.4343652752],"iteration":384,"passed_time":6.741360286,"remaining_time":10.76866643},
{"learn":[0.4343576879],"iteration":385,"passed_time":6.762229786,"remaining_time":10.75650023},
{"learn":[0.4343435309],"iteration":386,"passed_time":6.782205594,"remaining_time":10.74287346},
{"learn":[0.4343348309],"iteration":387,"passed_time":6.810572653,"remaining_time":10.74244965},
{"learn":[0.4343268121],"iteration":388,"passed_time":6.835353409,"remaining_time":10.73624919},
{"learn":[0.434321466],"iteration":389,"passed_time":6.864313638,"remaining_time":10.73649056},
{"learn":[0.434314811],"iteration":390,"passed_time":6.884670069,"remaining_time":10.72318177},
{"learn":[0.4343089674],"iteration":391,"passed_time":6.908075114,"remaining_time":10.71456548},
{"learn":[0.4342754026],"iteration":392,"passed_time":6.9269556,"remaining_time":10.69888562},
{"learn":[0.4342557899],"iteration":393,"passed_time":6.950668587,"remaining_time":10.69062224},
{"learn":[0.4342344092],"iteration":394,"passed_time":6.968774083,"remaining_time":10.67369195},
{"learn":[0.4342178156],"iteration":395,"passed_time":6.996931162,"remaining_time":10.67208692},
{"learn":[0.434206812],"iteration":396,"passed_time":7.020685811,"remaining_time":10.66366132},
{"learn":[0.4341888109],"iteration":397,"passed_time":7.049460594,"remaining_time":10.66275195},
{"learn":[0.4341560494],"iteration":398,"passed_time":7.080141185,"remaining_time":10.66457356},
{"learn":[0.4341278883],"iteration":399,"passed_time":7.099164205,"remaining_time":10.64874631},
{"learn":[0.4341149722],"iteration":400,"passed_time":7.131359031,"remaining_time":10.6525787},
{"learn":[0.4340914172],"iteration":401,"passed_time":7.161094367,"remaining_time":10.65257321},
{"learn":[0.4340766498],"iteration":402,"passed_time":7.181196029,"remaining_time":10.63814896},
{"learn":[0.4340686434],"iteration":403,"passed_time":7.204613166,"remaining_time":10.62858774},
{"learn":[0.4340421615],"iteration":404,"passed_time":7.228319885,"remaining_time":10.61938353},
{"learn":[0.4340258614],"iteration":405,"passed_time":7.2456607,"remaining_time":10.60079423},
{"learn":[0.434017002],"iteration":406,"passed_time":7.262081263,"remaining_time":10.58087024},
{"learn":[0.4339883428],"iteration":407,"passed_time":7.279756643,"remaining_time":10.56278415},
{"learn":[0.4339738168],"iteration":408,"passed_time":7.302026131,"remaining_time":10.55133849},
{"learn":[0.4339672924],"iteration":409,"passed_time":7.322388059,"remaining_time":10.53709501},
{"learn":[0.4339578697],"iteration":410,"passed_time":7.341625021,"remaining_time":10.52120958},
{"learn":[0.4339492256],"iteration":411,"passed_time":7.362065328,"remaining_time":10.50702527},
{"learn":[0.4339299777],"iteration":412,"passed_time":7.380896482,"remaining_time":10.49052357},
{"learn":[0.4339182951],"iteration":413,"passed_time":7.399602377,"remaining_time":10.47383332},
{"learn":[0.4338968606],"iteration":414,"passed_time":7.418912105,"remaining_time":10.45798453},
{"learn":[0.4338785937],"iteration":415,"passed_time":7.439972654,"remaining_time":10.444577},
{"learn":[0.4338747725],"iteration":416,"passed_time":7.458174919,"remaining_time":10.42713664},
{"learn":[0.4338490137],"iteration":417,"passed_time":7.474825381,"remaining_time":10.40753199},
{"learn":[0.4338413664],"iteration":418,"passed_time":7.494440611,"remaining_time":10.39205249},
{"learn":[0.4338245668],"iteration":419,"passed_time":7.509847748,"remaining_time":10.37074213},
{"learn":[0.4338138088],"iteration":420,"passed_time":7.522900369,"remaining_time":10.34622165},
{"learn":[0.4338077515],"iteration":421,"passed_time":7.535542757,"remaining_time":10.32119363},
{"learn":[0.4337833691],"iteration":422,"passed_time":7.550508524,"remaining_time":10.29939342},
{"learn":[0.4337700233],"iteration":423,"passed_time":7.568970276,"remaining_time":10.28237471},
{"learn":[0.4337487635],"iteration":424,"passed_time":7.586365655,"remaining_time":10.26390647},
{"learn":[0.4337399967],"iteration":425,"passed_time":7.602815655,"remaining_time":10.24416945},
{"learn":[0.4337313456],"iteration":426,"passed_time":7.625050533,"remaining_time":10.23221067},
{"learn":[0.4337077113],"iteration":427,"passed_time":7.645036417,"remaining_time":10.2171982},
{"learn":[0.433695853],"iteration":428,"passed_time":7.666728458,"remaining_time":10.20443345},
{"learn":[0.4336869926],"iteration":429,"passed_time":7.682961736,"remaining_time":10.18439114},
{"learn":[0.4336501105],"iteration":430,"passed_time":7.70364861,"remaining_time":10.17024608},
{"learn":[0.4336037466],"iteration":431,"passed_time":7.722468542,"remaining_time":10.15361605},
{"learn":[0.4335744018],"iteration":432,"passed_time":7.742879085,"remaining_time":10.13905876},
{"learn":[0.43356086],"iteration":433,"passed_time":7.764518658,"remaining_time":10.12607733},
{"learn":[0.4335484646],"iteration":434,"passed_time":7.787735916,"remaining_time":10.11510527},
{"learn":[0.4335090914],"iteration":435,"passed_time":7.807342294,"remaining_time":10.09940609},
{"learn":[0.4334907272],"iteration":436,"passed_time":7.826862297,"remaining_time":10.08357774},
{"learn":[0.4334753305],"iteration":437,"passed_time":7.846170374,"remaining_time":10.06746062},
{"learn":[0.4334289195],"iteration":438,"passed_time":7.865811599,"remaining_time":10.05175469},
{"learn":[0.4333911182],"iteration":439,"passed_time":7.885655475,"remaining_time":10.03628879},
{"learn":[0.4333843352],"iteration":440,"passed_time":7.904315045,"remaining_time":10.01930184},
{"learn":[0.4333774821],"iteration":441,"passed_time":7.929677515,"remaining_time":10.01076935},
{"learn":[0.4333578933],"iteration":442,"passed_time":7.95154829,"remaining_time":9.997770649},
{"learn":[0.4333510436],"iteration":443,"passed_time":7.974210387,"remaining_time":9.985722917},
{"learn":[0.4333447235],"iteration":444,"passed_time":7.998407884,"remaining_time":9.975542417},
{"learn":[0.4333299557],"iteration":445,"passed_time":8.023259704,"remaining_time":9.966111829},
{"learn":[0.4333068731],"iteration":446,"passed_time":8.042914309,"remaining_time":9.950182579},
{"learn":[0.4332844889],"iteration":447,"passed_time":8.068016097,"remaining_time":9.940948405},
{"learn":[0.4332724436],"iteration":448,"passed_time":8.091877973,"remaining_time":9.930121967},
{"learn":[0.4332613104],"iteration":449,"passed_time":8.111032121,"remaining_time":9.913483703},
{"learn":[0.4332549167],"iteration":450,"passed_time":8.133005495,"remaining_time":9.900266112},
{"learn":[0.4332515667],"iteration":451,"passed_time":8.156909072,"remaining_time":9.889349937},
{"learn":[0.4332454977],"iteration":452,"passed_time":8.184031344,"remaining_time":9.882263014},
{"learn":[0.4332389405],"iteration":453,"passed_time":8.20737354,"remaining_time":9.870541746},
{"learn":[0.4332300414],"iteration":454,"passed_time":8.231886705,"remaining_time":9.860171987},
{"learn":[0.4332177645],"iteration":455,"passed_time":8.250397427,"remaining_time":9.842579386},
{"learn":[0.4331981211],"iteration":456,"passed_time":8.27733662,"remaining_time":9.83499734},
{"learn":[0.4331891742],"iteration":457,"passed_time":8.303073346,"remaining_time":9.825907758},
{"learn":[0.4331624445],"iteration":458,"passed_time":8.326668106,"remaining_time":9.814221014},
{"learn":[0.4331504116],"iteration":459,"passed_time":8.347165299,"remaining_time":9.798846221},
{"learn":[0.4331478211],"iteration":460,"passed_time":8.368933296,"remaining_time":9.784935025},
{"learn":[0.4331427751],"iteration":461,"passed_time":8.388845882,"remaining_time":9.768829187},
{"learn":[0.4331341399],"iteration":462,"passed_time":8.409057205,"remaining_time":9.753053389},
{"learn":[0.4331295907],"iteration":463,"passed_time":8.432470288,"remaining_time":9.740957057},
{"learn":[0.4331266379],"iteration":464,"passed_time":8.452952683,"remaining_time":9.725440183},
{"learn":[0.4331176485],"iteration":465,"passed_time":8.473622072,"remaining_time":9.710116279},
{"learn":[0.4331077356],"iteration":466,"passed_time":8.492522218,"remaining_time":9.692750198},
{"learn":[0.4330891983],"iteration":467,"passed_time":8.517273438,"remaining_time":9.68202878},
{"learn":[0.4330844753],"iteration":468,"passed_time":8.541540104,"remaining_time":9.670698924},
{"learn":[0.4330738769],"iteration":469,"passed_time":8.561490647,"remaining_time":9.6544469},
{"learn":[0.4330667944],"iteration":470,"passed_time":8.578294632,"remaining_time":9.634645139},
{"learn":[0.4330636107],"iteration":471,"passed_time":8.595667618,"remaining_time":9.61549259},
{"learn":[0.4330586533],"iteration":472,"passed_time":8.622266697,"remaining_time":9.606626954},
{"learn":[0.433046565],"iteration":473,"passed_time":8.6456749,"remaining_time":9.594145565},
{"learn":[0.4330382216],"iteration":474,"passed_time":8.668434593,"remaining_time":9.580901392},
{"learn":[0.4330352037],"iteration":475,"passed_time":8.687034182,"remaining_time":9.563037629},
{"learn":[0.4330237762],"iteration":476,"passed_time":8.706890433,"remaining_time":9.54654863},
{"learn":[0.4330069667],"iteration":477,"passed_time":8.737575514,"remaining_time":9.541871168},
{"learn":[0.4330018048],"iteration":478,"passed_time":8.760962584,"remaining_time":9.529147194},
{"learn":[0.4329891981],"iteration":479,"passed_time":8.784942329,"remaining_time":9.517020857},
{"learn":[0.4329806584],"iteration":480,"passed_time":8.803459546,"remaining_time":9.498951153},
{"learn":[0.4329516627],"iteration":481,"passed_time":8.821254601,"remaining_time":9.480103492},
{"learn":[0.4329368309],"iteration":482,"passed_time":8.84483885,"remaining_time":9.467456905},
{"learn":[0.432915094],"iteration":483,"passed_time":8.864383039,"remaining_time":9.450457951},
{"learn":[0.4329105548],"iteration":484,"passed_time":8.883646544,"remaining_time":9.433150454},
{"learn":[0.4329032736],"iteration":485,"passed_time":8.904779821,"remaining_time":9.417812403},
{"learn":[0.4328925092],"iteration":486,"passed_time":8.921795231,"remaining_time":9.398112841},
{"learn":[0.4328830113],"iteration":487,"passed_time":8.937359006,"remaining_time":9.376901252},
{"learn":[0.4328781292],"iteration":488,"passed_time":8.961624058,"remaining_time":9.364805509},
{"learn":[0.4328651598],"iteration":489,"passed_time":8.979792915,"remaining_time":9.346315075},
{"learn":[0.4328593176],"iteration":490,"passed_time":8.9959925,"remaining_time":9.325784486},
{"learn":[0.4328524534],"iteration":491,"passed_time":9.012661847,"remaining_time":9.305756541},
{"learn":[0.4328455371],"iteration":492,"passed_time":9.031444603,"remaining_time":9.287915647},
{"learn":[0.4328307646],"iteration":493,"passed_time":9.050006409,"remaining_time":9.269844622},
{"learn":[0.4328243489],"iteration":494,"passed_time":9.065641299,"remaining_time":9.248785568},
{"learn":[0.4328211174],"iteration":495,"passed_time":9.080553238,"remaining_time":9.227013775},
{"learn":[0.4328174978],"iteration":496,"passed_time":9.096793745,"remaining_time":9.206614193},
{"learn":[0.4328132456],"iteration":497,"passed_time":9.113498471,"remaining_time":9.186699262},
{"learn":[0.4328035317],"iteration":498,"passed_time":9.128282025,"remaining_time":9.164868326},
{"learn":[0.4327983219],"iteration":499,"passed_time":9.143808666,"remaining_time":9.143808666},
{"learn":[0.4327966551],"iteration":500,"passed_time":9.159221917,"remaining_time":9.122658157},
{"learn":[0.4327835856],"iteration":501,"passed_time":9.179686258,"remaining_time":9.106541347},
{"learn":[0.4327747673],"iteration":502,"passed_time":9.198675603,"remaining_time":9.08894985},
{"learn":[0.4327666014],"iteration":503,"passed_time":9.214950613,"remaining_time":9.068681556},
{"learn":[0.4327569714],"iteration":504,"passed_time":9.232995394,"remaining_time":9.050163802},
{"learn":[0.4327419907],"iteration":505,"passed_time":9.25607432,"remaining_time":9.036562676},
{"learn":[0.4327384843],"iteration":506,"passed_time":9.273433027,"remaining_time":9.017361898},
{"learn":[0.4327247203],"iteration":507,"passed_time":9.292911682,"remaining_time":9.00022155},
{"learn":[0.4327215878],"iteration":508,"passed_time":9.313867673,"remaining_time":8.984497107},
{"learn":[0.4327165204],"iteration":509,"passed_time":9.336575698,"remaining_time":8.970435475},
{"learn":[0.4327114124],"iteration":510,"passed_time":9.353631166,"remaining_time":8.950930803},
{"learn":[0.4327017075],"iteration":511,"passed_time":9.373610977,"remaining_time":8.934222962},
{"learn":[0.4326972211],"iteration":512,"passed_time":9.392685822,"remaining_time":8.916643266},
{"learn":[0.4326908881],"iteration":513,"passed_time":9.409455719,"remaining_time":8.896878365},
{"learn":[0.4326808328],"iteration":514,"passed_time":9.426164396,"remaining_time":8.877067441},
{"learn":[0.4326730897],"iteration":515,"passed_time":9.442999293,"remaining_time":8.857386933},
{"learn":[0.4326620603],"iteration":516,"passed_time":9.459206747,"remaining_time":8.837131255},
{"learn":[0.4326602522],"iteration":517,"passed_time":9.472891108,"remaining_time":8.814543464},
{"learn":[0.4326541387],"iteration":518,"passed_time":9.488295351,"remaining_time":8.793583938},
{"learn":[0.4326514526],"iteration":519,"passed_time":9.502912119,"remaining_time":8.771918879},
{"learn":[0.4326396691],"iteration":520,"passed_time":9.517822793,"remaining_time":8.75055109},
{"learn":[0.4326344246],"iteration":521,"passed_time":9.532431742,"remaining_time":8.728931749},
{"learn":[0.4326248524],"iteration":522,"passed_time":9.544566543,"remaining_time":8.705082678},
{"learn":[0.4326112437],"iteration":523,"passed_time":9.559632575,"remaining_time":8.683941041},
{"learn":[0.4326059742],"iteration":524,"passed_time":9.574803676,"remaining_time":8.662917612},
{"learn":[0.4325996921],"iteration":525,"passed_time":9.592560326,"remaining_time":8.644246377},
{"learn":[0.4325936209],"iteration":526,"passed_time":9.614000244,"remaining_time":8.62888447},
{"learn":[0.4325770246],"iteration":527,"passed_time":9.632123654,"remaining_time":8.610534782},
{"learn":[0.4325713195],"iteration":528,"passed_time":9.652807432,"remaining_time":8.594465596},
{"learn":[0.4325588003],"iteration":529,"passed_time":9.672745527,"remaining_time":8.577717732},
{"learn":[0.4325580915],"iteration":530,"passed_time":9.695630176,"remaining_time":8.563560363},
{"learn":[0.4325520439],"iteration":531,"passed_time":9.715515266,"remaining_time":8.546731475},
{"learn":[0.4325438855],"iteration":532,"passed_time":9.73665665,"remaining_time":8.530991849},
{"learn":[0.4325392744],"iteration":533,"passed_time":9.754514641,"remaining_time":8.51236671},
{"learn":[0.4325348531],"iteration":534,"passed_time":9.771344561,"remaining_time":8.49285088},
{"learn":[0.4325307077],"iteration":535,"passed_time":9.788148253,"remaining_time":8.473322368},
{"learn":[0.4325249449],"iteration":536,"passed_time":9.805735227,"remaining_time":8.454479348},
{"learn":[0.4325208746],"iteration":537,"passed_time":9.821416479,"remaining_time":8.434004486},
{"learn":[0.4325183934],"iteration":538,"passed_time":9.834578196,"remaining_time":8.411392483},
{"learn":[0.4325152215],"iteration":539,"passed_time":9.848525232,"remaining_time":8.389484457},
{"learn":[0.4325134649],"iteration":540,"passed_time":9.862540693,"remaining_time":8.367663915},
{"learn":[0.4325082539],"iteration":541,"passed_time":9.875945359,"remaining_time":8.345356042},
{"learn":[0.4324951071],"iteration":542,"passed_time":9.887514413,"remaining_time":8.321536071},
{"learn":[0.4324866473],"iteration":543,"passed_time":9.903143914,"remaining_time":8.301164752},
{"learn":[0.4324724749],"iteration":544,"passed_time":9.918820417,"remaining_time":8.280850073},
{"learn":[0.4324641558],"iteration":545,"passed_time":9.934043377,"remaining_time":8.260175262},
{"learn":[0.4324617709],"iteration":546,"passed_time":9.95122214,"remaining_time":8.24114009},
{"learn":[0.432447029],"iteration":547,"passed_time":9.970894941,"remaining_time":8.22416882},
{"learn":[0.4324347734],"iteration":548,"passed_time":9.994522792,"remaining_time":8.210436756},
{"learn":[0.4324314295],"iteration":549,"passed_time":10.01801204,"remaining_time":8.196555302},
{"learn":[0.4324227759],"iteration":550,"passed_time":10.03958981,"remaining_time":8.181081355},
{"learn":[0.4324048328],"iteration":551,"passed_time":10.06093666,"remaining_time":8.165397871},
{"learn":[0.4323919144],"iteration":552,"passed_time":10.08352192,"remaining_time":8.150694934},
{"learn":[0.4323899669],"iteration":553,"passed_time":10.10094999,"remaining_time":8.131811726},
{"learn":[0.4323870638],"iteration":554,"passed_time":10.12465374,"remaining_time":8.117965611},
{"learn":[0.4323772715],"iteration":555,"passed_time":10.14819976,"remaining_time":8.103958081},
{"learn":[0.432348935],"iteration":556,"passed_time":10.17364722,"remaining_time":8.091428578},
{"learn":[0.4323444871],"iteration":557,"passed_time":10.199626,"remaining_time":8.079273639},
{"learn":[0.4323416399],"iteration":558,"passed_time":10.22798874,"remaining_time":8.06894997},
{"learn":[0.4323348188],"iteration":559,"passed_time":10.24705609,"remaining_time":8.051258354},
{"learn":[0.4323264376],"iteration":560,"passed_time":10.26588616,"remaining_time":8.033376155},
{"learn":[0.4323236684],"iteration":561,"passed_time":10.28626238,"remaining_time":8.016695593},
{"learn":[0.4323138302],"iteration":562,"passed_time":10.3067115,"remaining_time":8.000058479},
{"learn":[0.432308038],"iteration":563,"passed_time":10.32690968,"remaining_time":7.983213864},
{"learn":[0.4323058824],"iteration":564,"passed_time":10.34675706,"remaining_time":7.966087296},
{"learn":[0.4323038802],"iteration":565,"passed_time":10.36494324,"remaining_time":7.947677323},
{"learn":[0.4322968294],"iteration":566,"passed_time":10.38905676,"remaining_time":7.93379467},
{"learn":[0.4322926069],"iteration":567,"passed_time":10.41015617,"remaining_time":7.917583568},
{"learn":[0.4322883504],"iteration":568,"passed_time":10.4363954,"remaining_time":7.90524854},
{"learn":[0.4322809323],"iteration":569,"passed_time":10.45912242,"remaining_time":7.890215158},
{"learn":[0.432275254],"iteration":570,"passed_time":10.48026625,"remaining_time":7.873965359},
{"learn":[0.4322725148],"iteration":571,"passed_time":10.4990876,"remaining_time":7.855960649},
{"learn":[0.4322604],"iteration":572,"passed_time":10.51975944,"remaining_time":7.839332082},
{"learn":[0.4322559452],"iteration":573,"passed_time":10.54025264,"remaining_time":7.822556834},
{"learn":[0.4322539417],"iteration":574,"passed_time":10.5617989,"remaining_time":7.80654701},
{"learn":[0.4322465245],"iteration":575,"passed_time":10.58125824,"remaining_time":7.788981761},
{"learn":[0.432242286],"iteration":576,"passed_time":10.59430408,"remaining_time":7.766708189},
{"learn":[0.4322373384],"iteration":577,"passed_time":10.61112113,"remaining_time":7.747219925},
{"learn":[0.4322360722],"iteration":578,"passed_time":10.62621812,"remaining_time":7.726490206},
{"learn":[0.4322323879],"iteration":579,"passed_time":10.64630306,"remaining_time":7.709391872},
{"learn":[0.4322281856],"iteration":580,"passed_time":10.66548814,"remaining_time":7.691634305},
{"learn":[0.4322235375],"iteration":581,"passed_time":10.68112636,"remaining_time":7.671324433},
{"learn":[0.4322166652],"iteration":582,"passed_time":10.69708352,"remaining_time":7.65125871},
{"learn":[0.4322133908],"iteration":583,"passed_time":10.71924439,"remaining_time":7.635626139},
{"learn":[0.4322110497],"iteration":584,"passed_time":10.73718107,"remaining_time":7.616974605},
{"learn":[0.4322070221],"iteration":585,"passed_time":10.75600315,"remaining_time":7.598951029},
{"learn":[0.4321995011],"iteration":586,"passed_time":10.77331101,"remaining_time":7.579859364},
{"learn":[0.4321933201],"iteration":587,"passed_time":10.79150979,"remaining_time":7.561398018},
{"learn":[0.4321924947],"iteration":588,"passed_time":10.80824665,"remaining_time":7.541917444},
{"learn":[0.4321889638],"iteration":589,"passed_time":10.83096388,"remaining_time":7.52660202},
{"learn":[0.4321866997],"iteration":590,"passed_time":10.84931831,"remaining_time":7.508242283},
{"learn":[0.4321826803],"iteration":591,"passed_time":10.87005806,"remaining_time":7.491526502},
{"learn":[0.4321780581],"iteration":592,"passed_time":10.88806321,"remaining_time":7.472920282},
{"learn":[0.4321762402],"iteration":593,"passed_time":10.90611532,"remaining_time":7.454348185},
{"learn":[0.4321718874],"iteration":594,"passed_time":10.92769026,"remaining_time":7.438175722},
{"learn":[0.4321670041],"iteration":595,"passed_time":10.94636901,"remaining_time":7.420021945},
{"learn":[0.4321632891],"iteration":596,"passed_time":10.96640578,"remaining_time":7.402783133},
{"learn":[0.4321543794],"iteration":597,"passed_time":10.98684698,"remaining_time":7.385806834},
{"learn":[0.43215253],"iteration":598,"passed_time":11.00488802,"remaining_time":7.367212177},
{"learn":[0.43214549],"iteration":599,"passed_time":11.02183301,"remaining_time":7.347888671},
{"learn":[0.4321424862],"iteration":600,"passed_time":11.04190658,"remaining_time":7.330650126},
{"learn":[0.4321368285],"iteration":601,"passed_time":11.06073057,"remaining_time":7.312576026},
{"learn":[0.4321350668],"iteration":602,"passed_time":11.08064401,"remaining_time":7.295216705},
{"learn":[0.4321176228],"iteration":603,"passed_time":11.1009655,"remaining_time":7.278116456},
{"learn":[0.4321145919],"iteration":604,"passed_time":11.12073364,"remaining_time":7.260644277},
{"learn":[0.4321119204],"iteration":605,"passed_time":11.13993902,"remaining_time":7.242798637},
{"learn":[0.4321092099],"iteration":606,"passed_time":11.15777357,"remaining_time":7.224060975},
{"learn":[0.432106778],"iteration":607,"passed_time":11.17643425,"remaining_time":7.205858925},
{"learn":[0.4321048528],"iteration":608,"passed_time":11.19593127,"remaining_time":7.188192326},
{"learn":[0.4320989469],"iteration":609,"passed_time":11.21650286,"remaining_time":7.171206745},
{"learn":[0.4320962909],"iteration":610,"passed_time":11.24115087,"remaining_time":7.156804728},
{"learn":[0.4320926102],"iteration":611,"passed_time":11.26481493,"remaining_time":7.141745412},
{"learn":[0.4320894735],"iteration":612,"passed_time":11.29318035,"remaining_time":7.129626096},
{"learn":[0.4320846025],"iteration":613,"passed_time":11.31441172,"remaining_time":7.112968933},
{"learn":[0.4320784203],"iteration":614,"passed_time":11.35517784,"remaining_time":7.108525963},
{"learn":[0.43205694],"iteration":615,"passed_time":11.38678401,"remaining_time":7.098254965},
{"learn":[0.4320536658],"iteration":616,"passed_time":11.40935231,"remaining_time":7.082304594},
{"learn":[0.4320466375],"iteration":617,"passed_time":11.43450321,"remaining_time":7.067929169},
{"learn":[0.4320420221],"iteration":618,"passed_time":11.45892877,"remaining_time":7.053072477},
{"learn":[0.4320332752],"iteration":619,"passed_time":11.48456839,"remaining_time":7.038929011},
{"learn":[0.4320238635],"iteration":620,"passed_time":11.50890451,"remaining_time":7.023952996},
{"learn":[0.4320214227],"iteration":621,"passed_time":11.52669909,"remaining_time":7.004971475},
{"learn":[0.432020374],"iteration":622,"passed_time":11.54910164,"remaining_time":6.988782214},
{"learn":[0.4320174726],"iteration":623,"passed_time":11.5704909,"remaining_time":6.971962466},
{"learn":[0.432013555],"iteration":624,"passed_time":11.5906612,"remaining_time":6.954396717},
{"learn":[0.4320016131],"iteration":625,"passed_time":11.61000929,"remaining_time":6.936331428},
{"learn":[0.4319948136],"iteration":626,"passed_time":11.62746181,"remaining_time":6.917134376},
{"learn":[0.4319918049],"iteration":627,"passed_time":11.64972756,"remaining_time":6.900794033},
{"learn":[0.4319835174],"iteration":628,"passed_time":11.66669551,"remaining_time":6.881310073},
{"learn":[0.4319769206],"iteration":629,"passed_time":11.68835181,"remaining_time":6.864587571},
{"learn":[0.431975174],"iteration":630,"passed_time":11.7073442,"remaining_time":6.846291615},
{"learn":[0.4319725621],"iteration":631,"passed_time":11.72941588,"remaining_time":6.829786461},
{"learn":[0.4319675575],"iteration":632,"passed_time":11.74899261,"remaining_time":6.811817201},
{"learn":[0.4319659751],"iteration":633,"passed_time":11.77263041,"remaining_time":6.796187271},
{"learn":[0.4319614085],"iteration":634,"passed_time":11.79683907,"remaining_time":6.78086025},
{"learn":[0.4319592849],"iteration":635,"passed_time":11.82128127,"remaining_time":6.765638968},
{"learn":[0.4319524749],"iteration":636,"passed_time":11.83924324,"remaining_time":6.746695911},
{"learn":[0.4319466457],"iteration":637,"passed_time":11.85682311,"remaining_time":6.72753913},
{"learn":[0.4319415441],"iteration":638,"passed_time":11.87369016,"remaining_time":6.707984581},
{"learn":[0.4319398524],"iteration":639,"passed_time":11.89039195,"remaining_time":6.688345474},
{"learn":[0.4319341659],"iteration":640,"passed_time":11.90985447,"remaining_time":6.67026171},
{"learn":[0.4319297248],"iteration":641,"passed_time":11.9252287,"remaining_time":6.649893888},
{"learn":[0.4319250904],"iteration":642,"passed_time":11.94621006,"remaining_time":6.632654731},
{"learn":[0.4319157666],"iteration":643,"passed_time":11.96488381,"remaining_time":6.614128318},
{"learn":[0.431914092],"iteration":644,"passed_time":11.98600449,"remaining_time":6.596948209},
{"learn":[0.4319085517],"iteration":645,"passed_time":12.00387956,"remaining_time":6.577977346},
{"learn":[0.4319056068],"iteration":646,"passed_time":12.0207883,"remaining_time":6.558482641},
{"learn":[0.43190331],"iteration":647,"passed_time":12.04284617,"remaining_time":6.541792979},
{"learn":[0.4318996807],"iteration":648,"passed_time":12.05901343,"remaining_time":6.521900947},
{"learn":[0.4318945241],"iteration":649,"passed_time":12.07997026,"remaining_time":6.504599372},
{"learn":[0.4318919882],"iteration":650,"passed_time":12.09972858,"remaining_time":6.486644044},
{"learn":[0.4318823186],"iteration":651,"passed_time":12.12705746,"remaining_time":6.47272392},
{"learn":[0.4318804881],"iteration":652,"passed_time":12.1483298,"remaining_time":6.455544322},
{"learn":[0.4318739492],"iteration":653,"passed_time":12.16582383,"remaining_time":6.43635328},
{"learn":[0.4318720718],"iteration":654,"passed_time":12.19059268,"remaining_time":6.420999196},
{"learn":[0.4318698459],"iteration":655,"passed_time":12.21448621,"remaining_time":6.405157402},
{"learn":[0.4318691723],"iteration":656,"passed_time":12.23401526,"remaining_time":6.38701253},
{"learn":[0.4318647821],"iteration":657,"passed_time":12.25640903,"remaining_time":6.370352414},
{"learn":[0.4318629002],"iteration":658,"passed_time":12.28176748,"remaining_time":6.355208969},
{"learn":[0.4318561783],"iteration":659,"passed_time":12.30363086,"remaining_time":6.33823408},
{"learn":[0.4318499384],"iteration":660,"passed_time":12.33084286,"remaining_time":6.323987486},
{"learn":[0.4318462432],"iteration":661,"passed_time":12.35611093,"remaining_time":6.308709205},
{"learn":[0.4318305386],"iteration":662,"passed_time":12.38128976,"remaining_time":6.293355428},
{"learn":[0.4318255794],"iteration":663,"passed_time":12.40248708,"remaining_time":6.275957319},
{"learn":[0.4318189765],"iteration":664,"passed_time":12.42401566,"remaining_time":6.258714655},
{"learn":[0.4318171027],"iteration":665,"passed_time":12.44726945,"remaining_time":6.242324319},
{"learn":[0.4318128598],"iteration":666,"passed_time":12.47366351,"remaining_time":6.227481185},
{"learn":[0.431811221],"iteration":667,"passed_time":12.4988327,"remaining_time":6.211994694},
{"learn":[0.4318074047],"iteration":668,"passed_time":12.52482768,"remaining_time":6.196887837},
{"learn":[0.431806118],"iteration":669,"passed_time":12.54926181,"remaining_time":6.180979698},
{"learn":[0.4318039585],"iteration":670,"passed_time":12.5703492,"remaining_time":6.163405195},
{"learn":[0.431799323],"iteration":671,"passed_time":12.5891246,"remaining_time":6.14469177},
{"learn":[0.4317965336],"iteration":672,"passed_time":12.60862561,"remaining_time":6.126330721},
{"learn":[0.4317921174],"iteration":673,"passed_time":12.62662923,"remaining_time":6.107242032},
{"learn":[0.4317893921],"iteration":674,"passed_time":12.64695815,"remaining_time":6.089276145},
{"learn":[0.4317865907],"iteration":675,"passed_time":12.66815249,"remaining_time":6.071718056},
{"learn":[0.4317820411],"iteration":676,"passed_time":12.70394986,"remaining_time":6.061116405},
{"learn":[0.4317796228],"iteration":677,"passed_time":12.73570917,"remaining_time":6.048522643},
{"learn":[0.4317746698],"iteration":678,"passed_time":12.77626748,"remaining_time":6.040032195},
{"learn":[0.4317717084],"iteration":679,"passed_time":12.80670477,"remaining_time":6.026684598},
{"learn":[0.431769135],"iteration":680,"passed_time":12.8300283,"remaining_time":6.009954519},
{"learn":[0.4317664914],"iteration":681,"passed_time":12.84640616,"remaining_time":5.989966508},
{"learn":[0.4317639133],"iteration":682,"passed_time":12.86560119,"remaining_time":5.971296601},
{"learn":[0.4317606831],"iteration":683,"passed_time":12.88947856,"remaining_time":5.954788339},
{"learn":[0.4317584759],"iteration":684,"passed_time":12.91552087,"remaining_time":5.939254122},
{"learn":[0.4317577835],"iteration":685,"passed_time":12.94008717,"remaining_time":5.92301366},
{"learn":[0.431754747],"iteration":686,"passed_time":12.97161316,"remaining_time":5.909919824},
{"learn":[0.4317518656],"iteration":687,"passed_time":12.99947276,"remaining_time":5.895109742},
{"learn":[0.4317483692],"iteration":688,"passed_time":13.02220658,"remaining_time":5.877948106},
{"learn":[0.4317460825],"iteration":689,"passed_time":13.04340106,"remaining_time":5.860078739},
{"learn":[0.4317399536],"iteration":690,"passed_time":13.06484027,"remaining_time":5.842309178},
{"learn":[0.4317380254],"iteration":691,"passed_time":13.08043211,"remaining_time":5.821926432},
{"learn":[0.4317331644],"iteration":692,"passed_time":13.10373378,"remaining_time":5.804972972},
{"learn":[0.4317313535],"iteration":693,"passed_time":13.12674397,"remaining_time":5.787872703},
{"learn":[0.4317296908],"iteration":694,"passed_time":13.1452521,"remaining_time":5.768779697},
{"learn":[0.4317258549],"iteration":695,"passed_time":13.16932844,"remaining_time":5.75212047},
{"learn":[0.4317248076],"iteration":696,"passed_time":13.2043972,"remaining_time":5.740218582},
{"learn":[0.4317221714],"iteration":697,"passed_time":13.24735919,"remaining_time":5.731665437},
{"learn":[0.4317210834],"iteration":698,"passed_time":13.28348234,"remaining_time":5.720068932},
{"learn":[0.4317161651],"iteration":699,"passed_time":13.30518531,"remaining_time":5.702222274},
{"learn":[0.4317142051],"iteration":700,"passed_time":13.33223984,"remaining_time":5.686647237},
{"learn":[0.4317127405],"iteration":701,"passed_time":13.35866221,"remaining_time":5.670771138},
{"learn":[0.4317081854],"iteration":702,"passed_time":13.38273386,"remaining_time":5.653871914},
{"learn":[0.4316898893],"iteration":703,"passed_time":13.40569613,"remaining_time":5.636485874},
{"learn":[0.4316865072],"iteration":704,"passed_time":13.4468119,"remaining_time":5.626680155},
{"learn":[0.4316867462],"iteration":705,"passed_time":13.48486726,"remaining_time":5.615511296},
{"learn":[0.4316836513],"iteration":706,"passed_time":13.52755996,"remaining_time":5.606188215},
{"learn":[0.4316763081],"iteration":707,"passed_time":13.5757662,"remaining_time":5.599044819},
{"learn":[0.4316670623],"iteration":708,"passed_time":13.61555345,"remaining_time":5.588330119},
{"learn":[0.4316551564],"iteration":709,"passed_time":13.64641456,"remaining_time":5.573887638},
{"learn":[0.4316501248],"iteration":710,"passed_time":13.68549876,"remaining_time":5.56274141},
{"learn":[0.4316424432],"iteration":711,"passed_time":13.73286384,"remaining_time":5.554866271},
{"learn":[0.4316392685],"iteration":712,"passed_time":13.75708307,"remaining_time":5.537563591},
{"learn":[0.4316350782],"iteration":713,"passed_time":13.78089172,"remaining_time":5.520077077},
{"learn":[0.4316334035],"iteration":714,"passed_time":13.7956166,"remaining_time":5.498952071},
{"learn":[0.4316313172],"iteration":715,"passed_time":13.8072766,"remaining_time":5.476629264},
{"learn":[0.431627931],"iteration":716,"passed_time":13.81880423,"remaining_time":5.454283957},
{"learn":[0.431628419],"iteration":717,"passed_time":13.82799682,"remaining_time":5.431051676},
{"learn":[0.431626983],"iteration":718,"passed_time":13.83875051,"remaining_time":5.408468557},
{"learn":[0.4316246541],"iteration":719,"passed_time":13.85679749,"remaining_time":5.38875458},
{"learn":[0.4316233999],"iteration":720,"passed_time":13.89092239,"remaining_time":5.375266779},
{"learn":[0.4316228879],"iteration":721,"passed_time":13.92946379,"remaining_time":5.363422345},
{"learn":[0.4316215862],"iteration":722,"passed_time":13.95280049,"remaining_time":5.345678749},
{"learn":[0.4316184844],"iteration":723,"passed_time":13.97273034,"remaining_time":5.326620957},
{"learn":[0.4316184844],"iteration":724,"passed_time":13.98688679,"remaining_time":5.30537085},
{"learn":[0.431610003],"iteration":725,"passed_time":14.01125274,"remaining_time":5.287993456},
{"learn":[0.4316002],"iteration":726,"passed_time":14.03016369,"remaining_time":5.268548403},
{"learn":[0.431594914],"iteration":727,"passed_time":14.05241245,"remaining_time":5.250351903},
{"learn":[0.4315944691],"iteration":728,"passed_time":14.07970225,"remaining_time":5.234018256},
{"learn":[0.4315909406],"iteration":729,"passed_time":14.09871002,"remaining_time":5.214591377},
{"learn":[0.4315900914],"iteration":730,"passed_time":14.11426497,"remaining_time":5.193895045},
{"learn":[0.4315878297],"iteration":731,"passed_time":14.13254197,"remaining_time":5.174209357},
{"learn":[0.4315866807],"iteration":732,"passed_time":14.15345356,"remaining_time":5.155487176},
{"learn":[0.4315821012],"iteration":733,"passed_time":14.16471026,"remaining_time":5.133260123},
{"learn":[0.4315789141],"iteration":734,"passed_time":14.17879092,"remaining_time":5.112081079},
{"learn":[0.4315747055],"iteration":735,"passed_time":14.19582855,"remaining_time":5.091981978},
{"learn":[0.4315724047],"iteration":736,"passed_time":14.21044599,"remaining_time":5.071027537},
{"learn":[0.4315709809],"iteration":737,"passed_time":14.23070456,"remaining_time":5.052092948},
{"learn":[0.4315694219],"iteration":738,"passed_time":14.24649956,"remaining_time":5.03157833},
{"learn":[0.4315628008],"iteration":739,"passed_time":14.26294419,"remaining_time":5.011304715},
{"learn":[0.431559725],"iteration":740,"passed_time":14.27850412,"remaining_time":4.990732209},
{"learn":[0.4315555884],"iteration":741,"passed_time":14.29490718,"remaining_time":4.970466377},
{"learn":[0.4315499674],"iteration":742,"passed_time":14.31160578,"remaining_time":4.95031317},
{"learn":[0.4315467204],"iteration":743,"passed_time":14.34269349,"remaining_time":4.93512034},
{"learn":[0.4315408336],"iteration":744,"passed_time":14.38555966,"remaining_time":4.923916394},
{"learn":[0.4315391852],"iteration":745,"passed_time":14.42364747,"remaining_time":4.911000612},
{"learn":[0.4315367444],"iteration":746,"passed_time":14.45759973,"remaining_time":4.896616775},
{"learn":[0.4315361132],"iteration":747,"passed_time":14.48363247,"remaining_time":4.879512543},
{"learn":[0.4315331024],"iteration":748,"passed_time":14.51399272,"remaining_time":4.863834677},
{"learn":[0.431532375],"iteration":749,"passed_time":14.53364923,"remaining_time":4.844549743},
{"learn":[0.4315294616],"iteration":750,"passed_time":14.55328265,"remaining_time":4.825256166},
{"learn":[0.4315297562],"iteration":751,"passed_time":14.57161871,"remaining_time":4.805533829},
{"learn":[0.4315283652],"iteration":752,"passed_time":14.59716491,"remaining_time":4.788180257},
{"learn":[0.431526063],"iteration":753,"passed_time":14.62553257,"remaining_time":4.771725479},
{"learn":[0.4315245623],"iteration":754,"passed_time":14.65316376,"remaining_time":4.75500016},
{"learn":[0.4315149885],"iteration":755,"passed_time":14.67520301,"remaining_time":4.736441184},
{"learn":[0.431512847],"iteration":756,"passed_time":14.69694666,"remaining_time":4.717778122},
{"learn":[0.431510074],"iteration":757,"passed_time":14.72421163,"remaining_time":4.700869677},
{"learn":[0.4315090054],"iteration":758,"passed_time":14.74394682,"remaining_time":4.681543063},
{"learn":[0.4315046635],"iteration":759,"passed_time":14.76784296,"remaining_time":4.663529356},
{"learn":[0.4315021061],"iteration":760,"passed_time":14.79129328,"remaining_time":4.645360177},
{"learn":[0.431500591],"iteration":761,"passed_time":14.81721276,"remaining_time":4.627948342},
{"learn":[0.4314987335],"iteration":762,"passed_time":14.83794312,"remaining_time":4.608902383},
{"learn":[0.4314979859],"iteration":763,"passed_time":14.85869576,"remaining_time":4.5898589},
{"learn":[0.4314954006],"iteration":764,"passed_time":14.87627495,"remaining_time":4.569836096},
{"learn":[0.4314937734],"iteration":765,"passed_time":14.89369614,"remaining_time":4.549771407},
{"learn":[0.4314900765],"iteration":766,"passed_time":14.91011845,"remaining_time":4.529410167},
{"learn":[0.4314892734],"iteration":767,"passed_time":14.92772897,"remaining_time":4.509418127},
{"learn":[0.4314788357],"iteration":768,"passed_time":14.94739171,"remaining_time":4.490048746},
{"learn":[0.4314752502],"iteration":769,"passed_time":14.96566349,"remaining_time":4.470263119},
{"learn":[0.4314724114],"iteration":770,"passed_time":14.98660277,"remaining_time":4.451273716},
{"learn":[0.4314720184],"iteration":771,"passed_time":15.00118567,"remaining_time":4.430401986},
{"learn":[0.4314683316],"iteration":772,"passed_time":15.01916858,"remaining_time":4.410544977},
{"learn":[0.431467836],"iteration":773,"passed_time":15.03677563,"remaining_time":4.390583064},
{"learn":[0.4314655828],"iteration":774,"passed_time":15.0540721,"remaining_time":4.370537061},
{"learn":[0.4314645835],"iteration":775,"passed_time":15.07683239,"remaining_time":4.35207533},
{"learn":[0.4314623832],"iteration":776,"passed_time":15.09673313,"remaining_time":4.332781837},
{"learn":[0.4314599094],"iteration":777,"passed_time":15.11781898,"remaining_time":4.313824953},
{"learn":[0.4314559959],"iteration":778,"passed_time":15.13699835,"remaining_time":4.294321739},
{"learn":[0.4314554801],"iteration":779,"passed_time":15.15301722,"remaining_time":4.273927935},
{"learn":[0.4314538399],"iteration":780,"passed_time":15.16986989,"remaining_time":4.253779136},
{"learn":[0.4314402138],"iteration":781,"passed_time":15.18583428,"remaining_time":4.233391142},
{"learn":[0.4314383006],"iteration":782,"passed_time":15.20284594,"remaining_time":4.213304684},
{"learn":[0.4314374024],"iteration":783,"passed_time":15.22015878,"remaining_time":4.193309051},
{"learn":[0.4314361188],"iteration":784,"passed_time":15.2367558,"remaining_time":4.173124199},
{"learn":[0.4314310392],"iteration":785,"passed_time":15.26444482,"remaining_time":4.155968436},
{"learn":[0.4314305958],"iteration":786,"passed_time":15.28951187,"remaining_time":4.138076275},
{"learn":[0.4314302221],"iteration":787,"passed_time":15.31495988,"remaining_time":4.120268394},
{"learn":[0.4314236865],"iteration":788,"passed_time":15.34047233,"remaining_time":4.102458381},
{"learn":[0.4314196037],"iteration":789,"passed_time":15.36484506,"remaining_time":4.084325901},
{"learn":[0.4314139948],"iteration":790,"passed_time":15.3849498,"remaining_time":4.065049947},
{"learn":[0.4314133043],"iteration":791,"passed_time":15.41025827,"remaining_time":4.047138536},
{"learn":[0.4314119512],"iteration":792,"passed_time":15.43160409,"remaining_time":4.028174082},
{"learn":[0.4314113209],"iteration":793,"passed_time":15.45499489,"remaining_time":4.009734191},
{"learn":[0.4314074074],"iteration":794,"passed_time":15.4811113,"remaining_time":3.991984676},
{"learn":[0.4314069661],"iteration":795,"passed_time":15.50775267,"remaining_time":3.974348674},
{"learn":[0.4314056777],"iteration":796,"passed_time":15.52808731,"remaining_time":3.955083719},
{"learn":[0.4314045867],"iteration":797,"passed_time":15.55073298,"remaining_time":3.936401079},
{"learn":[0.4313954242],"iteration":798,"passed_time":15.57335199,"remaining_time":3.917701814},
{"learn":[0.4313948768],"iteration":799,"passed_time":15.59446739,"remaining_time":3.898616849},
{"learn":[0.4313919078],"iteration":800,"passed_time":15.61693626,"remaining_time":3.879863066},
{"learn":[0.4313914386],"iteration":801,"passed_time":15.63787869,"remaining_time":3.860723169},
{"learn":[0.4313888716],"iteration":802,"passed_time":15.65753025,"remaining_time":3.841262091},
{"learn":[0.4313878274],"iteration":803,"passed_time":15.6774077,"remaining_time":3.821855609},
{"learn":[0.4313873857],"iteration":804,"passed_time":15.69698975,"remaining_time":3.802376399},
{"learn":[0.4313866954],"iteration":805,"passed_time":15.71888981,"remaining_time":3.783454868},
{"learn":[0.4313859948],"iteration":806,"passed_time":15.73818362,"remaining_time":3.76390265},
{"learn":[0.4313756066],"iteration":807,"passed_time":15.7587497,"remaining_time":3.744653394},
{"learn":[0.4313746025],"iteration":808,"passed_time":15.7817064,"remaining_time":3.725965294},
{"learn":[0.431372863],"iteration":809,"passed_time":15.80333331,"remaining_time":3.706954726},
{"learn":[0.4313703117],"iteration":810,"passed_time":15.82150306,"remaining_time":3.687132034},
{"learn":[0.4313689207],"iteration":811,"passed_time":15.8385781,"remaining_time":3.667059954},
{"learn":[0.4313677631],"iteration":812,"passed_time":15.85574092,"remaining_time":3.647015439},
{"learn":[0.4313640617],"iteration":813,"passed_time":15.87383945,"remaining_time":3.627191815},
{"learn":[0.4313618967],"iteration":814,"passed_time":15.89678092,"remaining_time":3.608471744},
{"learn":[0.4313592818],"iteration":815,"passed_time":15.91257181,"remaining_time":3.588128938},
{"learn":[0.4313566378],"iteration":816,"passed_time":15.93474087,"remaining_time":3.569225924},
{"learn":[0.4313567521],"iteration":817,"passed_time":15.95180653,"remaining_time":3.549179447},
{"learn":[0.4313487878],"iteration":818,"passed_time":15.96931854,"remaining_time":3.529238897},
{"learn":[0.4313432556],"iteration":819,"passed_time":15.98638269,"remaining_time":3.509205957},
{"learn":[0.4313401943],"iteration":820,"passed_time":16.00198895,"remaining_time":3.48886239},
{"learn":[0.4313392159],"iteration":821,"passed_time":16.0180216,"remaining_time":3.468622683},
{"learn":[0.4313380889],"iteration":822,"passed_time":16.03742302,"remaining_time":3.449117709},
{"learn":[0.4313356865],"iteration":823,"passed_time":16.05447735,"remaining_time":3.429111668},
{"learn":[0.4313338167],"iteration":824,"passed_time":16.07255903,"remaining_time":3.409330703},
{"learn":[0.4313334702],"iteration":825,"passed_time":16.08958471,"remaining_time":3.389331403},
{"learn":[0.4313237934],"iteration":826,"passed_time":16.10986347,"remaining_time":3.370019807},
{"learn":[0.4313226089],"iteration":827,"passed_time":16.12868804,"remaining_time":3.350403795},
{"learn":[0.431320936],"iteration":828,"passed_time":16.15107618,"remaining_time":3.331524761},
{"learn":[0.4313208334],"iteration":829,"passed_time":16.1691567,"remaining_time":3.311754986},
{"learn":[0.4313191263],"iteration":830,"passed_time":16.1868049,"remaining_time":3.291901358},
{"learn":[0.4313184098],"iteration":831,"passed_time":16.20305097,"remaining_time":3.271769908},
{"learn":[0.4313174109],"iteration":832,"passed_time":16.21999685,"remaining_time":3.251788083},
{"learn":[0.431316909],"iteration":833,"passed_time":16.23825441,"remaining_time":3.232074619},
{"learn":[0.4313153614],"iteration":834,"passed_time":16.25879962,"remaining_time":3.212816692},
{"learn":[0.4313142121],"iteration":835,"passed_time":16.28319095,"remaining_time":3.194310186},
{"learn":[0.4313125818],"iteration":836,"passed_time":16.30668619,"remaining_time":3.175615113},
{"learn":[0.4313121768],"iteration":837,"passed_time":16.33049047,"remaining_time":3.156968324},
{"learn":[0.4313062501],"iteration":838,"passed_time":16.34932302,"remaining_time":3.137355192},
{"learn":[0.4313033061],"iteration":839,"passed_time":16.36878344,"remaining_time":3.117863512},
{"learn":[0.431301069],"iteration":840,"passed_time":16.38875382,"remaining_time":3.098468321},
{"learn":[0.4312973874],"iteration":841,"passed_time":16.41377819,"remaining_time":3.080020135},
{"learn":[0.4312944403],"iteration":842,"passed_time":16.43208983,"remaining_time":3.060306173},
{"learn":[0.4312927466],"iteration":843,"passed_time":16.45262287,"remaining_time":3.041006123},
{"learn":[0.4312929872],"iteration":844,"passed_time":16.47211242,"remaining_time":3.021511747},
{"learn":[0.4312905086],"iteration":845,"passed_time":16.49247393,"remaining_time":3.002176106},
{"learn":[0.4312859987],"iteration":846,"passed_time":16.51198767,"remaining_time":2.982684903},
{"learn":[0.4312835872],"iteration":847,"passed_time":16.53585666,"remaining_time":2.963974306},
{"learn":[0.4312820981],"iteration":848,"passed_time":16.55747164,"remaining_time":2.944850669},
{"learn":[0.4312808716],"iteration":849,"passed_time":16.57683527,"remaining_time":2.925323871},
{"learn":[0.4312800486],"iteration":850,"passed_time":16.59362722,"remaining_time":2.905347186},
{"learn":[0.4312776145],"iteration":851,"passed_time":16.61252019,"remaining_time":2.885742943},
{"learn":[0.4312756203],"iteration":852,"passed_time":16.63410646,"remaining_time":2.866604513},
{"learn":[0.4312747904],"iteration":853,"passed_time":16.6523607,"remaining_time":2.846890704},
{"learn":[0.4312694569],"iteration":854,"passed_time":16.67337963,"remaining_time":2.827649177},
{"learn":[0.4312687585],"iteration":855,"passed_time":16.69211424,"remaining_time":2.808019218},
{"learn":[0.431266091],"iteration":856,"passed_time":16.71290831,"remaining_time":2.788734992},
{"learn":[0.4312616053],"iteration":857,"passed_time":16.73410251,"remaining_time":2.769513469},
{"learn":[0.4312603689],"iteration":858,"passed_time":16.75704042,"remaining_time":2.750573572},
{"learn":[0.4312579721],"iteration":859,"passed_time":16.77568671,"remaining_time":2.730925744},
{"learn":[0.4312561038],"iteration":860,"passed_time":16.80936276,"remaining_time":2.713706648},
{"learn":[0.4312543449],"iteration":861,"passed_time":16.84106564,"remaining_time":2.696133479},
{"learn":[0.4312551692],"iteration":862,"passed_time":16.87130747,"remaining_time":2.678295624},
{"learn":[0.4312422031],"iteration":863,"passed_time":16.89995107,"remaining_time":2.660177483},
{"learn":[0.4312410262],"iteration":864,"passed_time":16.9232889,"remaining_time":2.641206938},
{"learn":[0.4312395853],"iteration":865,"passed_time":16.94777828,"remaining_time":2.622404491},
{"learn":[0.4312357292],"iteration":866,"passed_time":16.97241512,"remaining_time":2.603611547},
{"learn":[0.4312354882],"iteration":867,"passed_time":16.99537717,"remaining_time":2.584550446},
{"learn":[0.4312344848],"iteration":868,"passed_time":17.02182175,"remaining_time":2.56600535},
{"learn":[0.431233624],"iteration":869,"passed_time":17.0509412,"remaining_time":2.547841789},
{"learn":[0.4312324842],"iteration":870,"passed_time":17.07801551,"remaining_time":2.529350172},
{"learn":[0.4312318752],"iteration":871,"passed_time":17.11765131,"remaining_time":2.512682761},
{"learn":[0.4312311948],"iteration":872,"passed_time":17.14841408,"remaining_time":2.494671922},
{"learn":[0.431229926],"iteration":873,"passed_time":17.17206442,"remaining_time":2.475606542},
{"learn":[0.4312294279],"iteration":874,"passed_time":17.19661003,"remaining_time":2.456658575},
{"learn":[0.4312276447],"iteration":875,"passed_time":17.21603611,"remaining_time":2.436973148},
{"learn":[0.4312260123],"iteration":876,"passed_time":17.24361182,"remaining_time":2.418431304},
{"learn":[0.431224567],"iteration":877,"passed_time":17.27008104,"remaining_time":2.399715133},
{"learn":[0.4312253794],"iteration":878,"passed_time":17.29220959,"remaining_time":2.380383801},
{"learn":[0.4312238136],"iteration":879,"passed_time":17.31420352,"remaining_time":2.361027753},
{"learn":[0.4312237153],"iteration":880,"passed_time":17.33183731,"remaining_time":2.341076776},
{"learn":[0.4312239281],"iteration":881,"passed_time":17.34996925,"remaining_time":2.3211977},
{"learn":[0.4312223379],"iteration":882,"passed_time":17.41626903,"remaining_time":2.307704957},
{"learn":[0.4312210804],"iteration":883,"passed_time":17.45504242,"remaining_time":2.290480679},
{"learn":[0.4312204496],"iteration":884,"passed_time":17.47655723,"remaining_time":2.270965063},
{"learn":[0.4312192912],"iteration":885,"passed_time":17.50422361,"remaining_time":2.252236446},
{"learn":[0.431217814],"iteration":886,"passed_time":17.52296344,"remaining_time":2.232350471},
{"learn":[0.4312173965],"iteration":887,"passed_time":17.54058233,"remaining_time":2.212325699},
{"learn":[0.4312169483],"iteration":888,"passed_time":17.56698436,"remaining_time":2.193402997},
{"learn":[0.4312150936],"iteration":889,"passed_time":17.59040477,"remaining_time":2.174094972},
{"learn":[0.4312131029],"iteration":890,"passed_time":17.61572117,"remaining_time":2.15500966},
{"learn":[0.4312122353],"iteration":891,"passed_time":17.6421286,"remaining_time":2.136042476},
{"learn":[0.4312112456],"iteration":892,"passed_time":17.66445543,"remaining_time":2.116569687},
{"learn":[0.4312113441],"iteration":893,"passed_time":17.67942705,"remaining_time":2.09621842},
{"learn":[0.4312063896],"iteration":894,"passed_time":17.6978303,"remaining_time":2.076281767},
{"learn":[0.4312068349],"iteration":895,"passed_time":17.71293439,"remaining_time":2.055965598},
{"learn":[0.431205962],"iteration":896,"passed_time":17.74231286,"remaining_time":2.037300139},
{"learn":[0.4312054324],"iteration":897,"passed_time":17.76159078,"remaining_time":2.01746354},
{"learn":[0.431205437],"iteration":898,"passed_time":17.7872715,"remaining_time":1.998347521},
{"learn":[0.4312042839],"iteration":899,"passed_time":17.80517866,"remaining_time":1.978353184},
{"learn":[0.4312033638],"iteration":900,"passed_time":17.8273922,"remaining_time":1.958836657},
{"learn":[0.4312035896],"iteration":901,"passed_time":17.84333053,"remaining_time":1.938632364},
{"learn":[0.431202766],"iteration":902,"passed_time":17.8606443,"remaining_time":1.918585268},
{"learn":[0.4312025051],"iteration":903,"passed_time":17.88334124,"remaining_time":1.899115883},
{"learn":[0.4312011774],"iteration":904,"passed_time":17.90967874,"remaining_time":1.880021525},
{"learn":[0.4312000988],"iteration":905,"passed_time":17.93306845,"remaining_time":1.860605336},
{"learn":[0.4311986598],"iteration":906,"passed_time":17.96087637,"remaining_time":1.841633409},
{"learn":[0.4311985245],"iteration":907,"passed_time":17.98712634,"remaining_time":1.822484167},
{"learn":[0.4311981604],"iteration":908,"passed_time":18.01332301,"remaining_time":1.803313965},
{"learn":[0.431197339],"iteration":909,"passed_time":18.03828118,"remaining_time":1.784005831},
{"learn":[0.4311972447],"iteration":910,"passed_time":18.06578963,"remaining_time":1.764934442},
{"learn":[0.4311975357],"iteration":911,"passed_time":18.08770237,"remaining_time":1.745304615},
{"learn":[0.4311966598],"iteration":912,"passed_time":18.11502159,"remaining_time":1.72618497},
{"learn":[0.4311946535],"iteration":913,"passed_time":18.14017402,"remaining_time":1.706843507},
{"learn":[0.4311953454],"iteration":914,"passed_time":18.16314228,"remaining_time":1.687286441},
{"learn":[0.4311941324],"iteration":915,"passed_time":18.18842074,"remaining_time":1.667933779},
{"learn":[0.4311934222],"iteration":916,"passed_time":18.21196989,"remaining_time":1.64841167},
{"learn":[0.4311927711],"iteration":917,"passed_time":18.23206672,"remaining_time":1.628572408},
{"learn":[0.4311916375],"iteration":918,"passed_time":18.25285341,"remaining_time":1.608793391},
{"learn":[0.4311904952],"iteration":919,"passed_time":18.27672959,"remaining_time":1.589280834},
{"learn":[0.4311891284],"iteration":920,"passed_time":18.30285899,"remaining_time":1.569952074},
{"learn":[0.4311891648],"iteration":921,"passed_time":18.32677365,"remaining_time":1.550421198},
{"learn":[0.4311882429],"iteration":922,"passed_time":18.35067763,"remaining_time":1.530879932},
{"learn":[0.4311865886],"iteration":923,"passed_time":18.37423511,"remaining_time":1.511300723},
{"learn":[0.4311856958],"iteration":924,"passed_time":18.38940761,"remaining_time":1.491033049},
{"learn":[0.4311848],"iteration":925,"passed_time":18.41302166,"remaining_time":1.471450975},
{"learn":[0.4311849927],"iteration":926,"passed_time":18.4319765,"remaining_time":1.451493295},
{"learn":[0.4311843175],"iteration":927,"passed_time":18.4495743,"remaining_time":1.431432489},
{"learn":[0.4311836856],"iteration":928,"passed_time":18.46763438,"remaining_time":1.411412315},
{"learn":[0.4311788356],"iteration":929,"passed_time":18.49546451,"remaining_time":1.392131737},
{"learn":[0.431178535],"iteration":930,"passed_time":18.51500202,"remaining_time":1.372218195},
{"learn":[0.4311739554],"iteration":931,"passed_time":18.53640964,"remaining_time":1.352441905},
{"learn":[0.4311736457],"iteration":932,"passed_time":18.55786467,"remaining_time":1.332665523},
{"learn":[0.4311719869],"iteration":933,"passed_time":18.57663289,"remaining_time":1.312695686},
{"learn":[0.4311693722],"iteration":934,"passed_time":18.5966414,"remaining_time":1.292814643},
{"learn":[0.4311682952],"iteration":935,"passed_time":18.61943696,"remaining_time":1.273123895},
{"learn":[0.4311679498],"iteration":936,"passed_time":18.63936987,"remaining_time":1.253234047},
{"learn":[0.4311662392],"iteration":937,"passed_time":18.6613658,"remaining_time":1.233480469},
{"learn":[0.431166059],"iteration":938,"passed_time":18.6788074,"remaining_time":1.213426253},
{"learn":[0.4311648528],"iteration":939,"passed_time":18.69420309,"remaining_time":1.193247005},
{"learn":[0.431161457],"iteration":940,"passed_time":18.71139609,"remaining_time":1.173190615},
{"learn":[0.4311599608],"iteration":941,"passed_time":18.7270165,"remaining_time":1.153043479},
{"learn":[0.4311596016],"iteration":942,"passed_time":18.7444553,"remaining_time":1.133015856},
{"learn":[0.4311563564],"iteration":943,"passed_time":18.76129848,"remaining_time":1.112958384},
{"learn":[0.4311552933],"iteration":944,"passed_time":18.77785087,"remaining_time":1.092890791},
{"learn":[0.4311543759],"iteration":945,"passed_time":18.79414839,"remaining_time":1.072816082},
{"learn":[0.4311523521],"iteration":946,"passed_time":18.81074519,"remaining_time":1.052766098},
{"learn":[0.4311502879],"iteration":947,"passed_time":18.82670057,"remaining_time":1.032688217},
{"learn":[0.4311505006],"iteration":948,"passed_time":18.84247312,"remaining_time":1.012609198},
{"learn":[0.4311484519],"iteration":949,"passed_time":18.85817615,"remaining_time":0.992535587},
{"learn":[0.4311466948],"iteration":950,"passed_time":18.8745464,"remaining_time":0.9725055455},
{"learn":[0.4311458952],"iteration":951,"passed_time":18.89136933,"remaining_time":0.9525060167},
{"learn":[0.4311428208],"iteration":952,"passed_time":18.90795132,"remaining_time":0.932501272},
{"learn":[0.4311436882],"iteration":953,"passed_time":18.91998599,"remaining_time":0.9122844398},
{"learn":[0.4311397027],"iteration":954,"passed_time":18.93908812,"remaining_time":0.8924177649},
{"learn":[0.4311392717],"iteration":955,"passed_time":18.95831506,"remaining_time":0.8725584337},
{"learn":[0.4311379058],"iteration":956,"passed_time":18.97680888,"remaining_time":0.8526674834},
{"learn":[0.4311383137],"iteration":957,"passed_time":18.99149264,"remaining_time":0.8326124121},
{"learn":[0.4311365965],"iteration":958,"passed_time":19.00844227,"remaining_time":0.8126654152},
{"learn":[0.431133145],"iteration":959,"passed_time":19.02878131,"remaining_time":0.7928658878},
{"learn":[0.4311325834],"iteration":960,"passed_time":19.05302427,"remaining_time":0.7732236697},
{"learn":[0.4311224988],"iteration":961,"passed_time":19.07229271,"remaining_time":0.7533753878},
{"learn":[0.4311221973],"iteration":962,"passed_time":19.09066565,"remaining_time":0.7334939036},
{"learn":[0.4311214642],"iteration":963,"passed_time":19.11218116,"remaining_time":0.7137329064},
{"learn":[0.4311206604],"iteration":964,"passed_time":19.13478653,"remaining_time":0.6940078017},
{"learn":[0.431118671],"iteration":965,"passed_time":19.15273938,"remaining_time":0.6741129802},
{"learn":[0.431116627],"iteration":966,"passed_time":19.17187517,"remaining_time":0.6542625445},
{"learn":[0.4311159203],"iteration":967,"passed_time":19.18982834,"remaining_time":0.6343744907},
{"learn":[0.4311135926],"iteration":968,"passed_time":19.21049473,"remaining_time":0.6145772309},
{"learn":[0.4311111274],"iteration":969,"passed_time":19.23339387,"remaining_time":0.5948472331},
{"learn":[0.4311117077],"iteration":970,"passed_time":19.2530809,"remaining_time":0.5750147747},
{"learn":[0.4311100157],"iteration":971,"passed_time":19.28000402,"remaining_time":0.5553910623},
{"learn":[0.4311083105],"iteration":972,"passed_time":19.30217387,"remaining_time":0.5356204467},
{"learn":[0.4311068346],"iteration":973,"passed_time":19.32076461,"remaining_time":0.5157493634},
{"learn":[0.4311061453],"iteration":974,"passed_time":19.34279266,"remaining_time":0.4959690426},
{"learn":[0.4311054588],"iteration":975,"passed_time":19.3638085,"remaining_time":0.4761592255},
{"learn":[0.431101985],"iteration":976,"passed_time":19.38446686,"remaining_time":0.4563385239},
{"learn":[0.4310951027],"iteration":977,"passed_time":19.40369143,"remaining_time":0.4364838563},
{"learn":[0.4310938239],"iteration":978,"passed_time":19.42431019,"remaining_time":0.4166603821},
{"learn":[0.4310924211],"iteration":979,"passed_time":19.44502102,"remaining_time":0.3968371637},
{"learn":[0.4310933109],"iteration":980,"passed_time":19.4653108,"remaining_time":0.3770039809},
{"learn":[0.4310931142],"iteration":981,"passed_time":19.48198627,"remaining_time":0.357103618},
{"learn":[0.4310922193],"iteration":982,"passed_time":19.50136091,"remaining_time":0.337256496},
{"learn":[0.4310912901],"iteration":983,"passed_time":19.52355948,"remaining_time":0.3174562518},
{"learn":[0.4310905952],"iteration":984,"passed_time":19.54479852,"remaining_time":0.2976365257},
{"learn":[0.431090025],"iteration":985,"passed_time":19.57104481,"remaining_time":0.2778850176},
{"learn":[0.4310901691],"iteration":986,"passed_time":19.58942562,"remaining_time":0.2580167509},
{"learn":[0.4310886089],"iteration":987,"passed_time":19.60893126,"remaining_time":0.238165157},
{"learn":[0.4310875769],"iteration":988,"passed_time":19.63016531,"remaining_time":0.2183334867},
{"learn":[0.4310849513],"iteration":989,"passed_time":19.65841066,"remaining_time":0.1985698046},
{"learn":[0.4310846352],"iteration":990,"passed_time":19.67592911,"remaining_time":0.1786915862},
{"learn":[0.4310844751],"iteration":991,"passed_time":19.69808761,"remaining_time":0.1588555452},
{"learn":[0.4310836424],"iteration":992,"passed_time":19.72202477,"remaining_time":0.1390273649},
{"learn":[0.4310823896],"iteration":993,"passed_time":19.74665697,"remaining_time":0.1191951125},
{"learn":[0.431082148],"iteration":994,"passed_time":19.76827713,"remaining_time":0.09933807602},
{"learn":[0.4310810507],"iteration":995,"passed_time":19.79411305,"remaining_time":0.07949442994},
{"learn":[0.4310816356],"iteration":996,"passed_time":19.81526728,"remaining_time":0.05962467585},
{"learn":[0.4310782958],"iteration":997,"passed_time":19.83350833,"remaining_time":0.03974650969},
{"learn":[0.4310785042],"iteration":998,"passed_time":19.8579088,"remaining_time":0.01987778658},
{"learn":[0.4310779647],"iteration":999,"passed_time":19.8771377,"remaining_time":0}
]}